Workbook

Sheet Read_Me
A1: CE725 Topic 5: Manual validation workbook
A2: Plain Excel formulas only. Excel recalculates everything here independently of the Python tool.
A4: Colour legend
A5: Yellow cells | B5: Fill in: your hand calculations (paper or calculator) and tool values from scripts/export_validation_values.py
A6: Blue numbers | B6: Inputs typed in (benchmark ranges, finance inputs, activity data)
A7: Green text | B7: Links to another sheet
A8: Black | B8: Formulas: do not overwrite
A10: Order of work
A11: 1. T1_PERT | B11: Do the PERT means by hand on paper first, type them in the yellow column, then compare with Excel and the tool.
A12: 2. T2_CPM | B12: Do the forward and backward pass by hand for the most-likely case, then compare.
A13: 3. T3_MonteCarlo | B13: 5,000-run simulation in Excel with RAND() and BETAINV. Press F9 to re-run; results move slightly each time, which is why tolerances are used.
A14: 4. T4_Correlated | B14: Optional: B and D correlated at 0.6 using a hand-built 2x2 Cholesky step. Checks the tool's correlation method.
A15: 5. Fin_Inputs + Fin_Activities | B15: Paste your verified finance inputs and activity data (same values as the tool's data folder).
A16: 6. Fin_CashFlow | B16: Monthly cash flow, debt, NPV and IRR. Compare with the tool. Then do the hand checks at the bottom by calculator.
A17: 7. Scenarios | B17: Set cost multiplier to 1.10 for the flat-10% test (T20), then delay days to 60 for the delay test (T21). Reset to 1 and 0 afterwards.
A18: 8. Summary | B18: All results in one place. Copy each into the Validation tab of the tracking workbook, with cause and fix for any Fail.
A20: Updating tool values | B20: After any data change run: python scripts/export_validation_values.py and copy results/validation_tool_values.csv values into the yellow Tool value cells (they are pre-filled for the data the workbook was built with).
A21: Independence | B21: The tool and this workbook were both written with AI help (log this). The hand calculations in the yellow columns are what make this a genuine manual check, so do them yourselves before looking at the Excel column.
A22: Speed | B22: The two simulation sheets recalculate on every edit. If Excel feels slow: Formulas > Calculation Options > Manual, then press F9 when you want to recalculate.

Sheet Summary
A1: Validation summary
A2: Copy each row into the Validation tab of the tracking workbook. Finance rows show the scenario currently set in Fin_Inputs.
A3: Finance scenario now: | B3: =Fin_CashFlow!C27 -> Plan
A5: Test | B5: What | C5: Excel | D5: Tool | E5: Difference | F5: Tolerance | G5: Result
A6: T01A | B6: Simulated mean of A vs PERT mean | C6: =T1_PERT!H5 -> 4 | D6: =T1_PERT!L5 -> 3.9985049 | E6: =IF(OR(C6="",D6=""),"",ABS(C6-D6)) -> 0.0014951054 | F6: =T1_PERT!N5 -> 0.02 | G6: =IF(D6="","Pending",IF(E6<=F6,"Pass","Fail")) -> Pass
A7: T01B | B7: Simulated mean of B vs PERT mean | C7: =T1_PERT!H6 -> 5.3333333 | D7: =T1_PERT!L6 -> 5.3371195 | E7: =IF(OR(C7="",D7=""),"",ABS(C7-D7)) -> 0.0037861225 | F7: =T1_PERT!N6 -> 0.02 | G7: =IF(D7="","Pending",IF(E7<=F7,"Pass","Fail")) -> Pass
A8: T01C | B8: Simulated mean of C vs PERT mean | C8: =T1_PERT!H7 -> 5.6666667 | D8: =T1_PERT!L7 -> 5.6652818 | E8: =IF(OR(C8="",D8=""),"",ABS(C8-D8)) -> 0.0013848689 | F8: =T1_PERT!N7 -> 0.02 | G8: =IF(D8="","Pending",IF(E8<=F8,"Pass","Fail")) -> Pass
A9: T01D | B9: Simulated mean of D vs PERT mean | C9: =T1_PERT!H8 -> 5.3333333 | D9: =T1_PERT!L8 -> 5.334063 | E9: =IF(OR(C9="",D9=""),"",ABS(C9-D9)) -> 0.00072968942 | F9: =T1_PERT!N8 -> 0.02 | G9: =IF(D9="","Pending",IF(E9<=F9,"Pass","Fail")) -> Pass
A10: T01E | B10: Simulated mean of E vs PERT mean | C10: =T1_PERT!H9 -> 4.3333333 | D10: =T1_PERT!L9 -> 4.3336108 | E10: =IF(OR(C10="",D10=""),"",ABS(C10-D10)) -> 0.00027744782 | F10: =T1_PERT!N9 -> 0.02 | G10: =IF(D10="","Pending",IF(E10<=F10,"Pass","Fail")) -> Pass
A11: T01F | B11: Simulated mean of F vs PERT mean | C11: =T1_PERT!H10 -> 2 | D11: =T1_PERT!L10 -> 2.0001043 | E11: =IF(OR(C11="",D11=""),"",ABS(C11-D11)) -> 0.00010426561 | F11: =T1_PERT!N10 -> 0.02 | G11: =IF(D11="","Pending",IF(E11<=F11,"Pass","Fail")) -> Pass
A12: T02 | B12: Project duration, most-likely (days) | C12: =T2_CPM!C27 -> 16 | D12: =T2_CPM!E27 -> 16 | E12: =IF(OR(C12="",D12=""),"",ABS(C12-D12)) -> 0 | F12: =T2_CPM!F27 -> 0.001 | G12: =IF(D12="","Pending",IF(E12<=F12,"Pass","Fail")) -> Pass
A13: T03 | B13: Project duration, PERT on one critical path (days) | C13: =T2_CPM!C28 -> 16.666667 | D13: =T2_CPM!E28 -> 16.666667 | E13: =IF(OR(C13="",D13=""),"",ABS(C13-D13)) -> 0 | F13: =T2_CPM!F28 -> 0.001 | G13: =IF(D13="","Pending",IF(E13<=F13,"Pass","Fail")) -> Pass
A14: T04 | B14: Mean project duration | C14: =T3_MonteCarlo!C5 -> 17.120653 | D14: =T3_MonteCarlo!D5 -> 17.122409 | E14: =IF(OR(C14="",D14=""),"",ABS(C14-D14)) -> 0.0017561564 | F14: =T3_MonteCarlo!F5 -> 0.1 | G14: =IF(D14="","Pending",IF(E14<=F14,"Pass","Fail")) -> Pass
A15: T05b | B15: P50 project duration | C15: =T3_MonteCarlo!C6 -> 17.11695 | D15: =T3_MonteCarlo!D6 -> 17.098149 | E15: =IF(OR(C15="",D15=""),"",ABS(C15-D15)) -> 0.018800633 | F15: =T3_MonteCarlo!F6 -> 0.15 | G15: =IF(D15="","Pending",IF(E15<=F15,"Pass","Fail")) -> Pass
A16: T05 | B16: P80 project duration | C16: =T3_MonteCarlo!C7 -> 18.301044 | D16: =T3_MonteCarlo!D7 -> 18.308138 | E16: =IF(OR(C16="",D16=""),"",ABS(C16-D16)) -> 0.0070937073 | F16: =T3_MonteCarlo!F7 -> 0.15 | G16: =IF(D16="","Pending",IF(E16<=F16,"Pass","Fail")) -> Pass
A17: T05c | B17: P90 project duration | C17: =T3_MonteCarlo!C8 -> 18.949934 | D17: =T3_MonteCarlo!D8 -> 18.944659 | E17: =IF(OR(C17="",D17=""),"",ABS(C17-D17)) -> 0.0052750866 | F17: =T3_MonteCarlo!F8 -> 0.2 | G17: =IF(D17="","Pending",IF(E17<=F17,"Pass","Fail")) -> Pass
A18: T06 | B18: Criticality index of B (share of runs A-B-D-F is longest) | C18: =T3_MonteCarlo!C9 -> 0.6322 | D18: =T3_MonteCarlo!D9 -> 0.63011 | E18: =IF(OR(C18="",D18=""),"",ABS(C18-D18)) -> 0.00209 | F18: =T3_MonteCarlo!F9 -> 0.03 | G18: =IF(D18="","Pending",IF(E18<=F18,"Pass","Fail")) -> Pass
A19: T09 | B19: Rank correlation of B and D (CORREL of their uniforms) | C19: =T4_Correlated!C6 -> 0.58410298 | D19: =T4_Correlated!D6 -> 0.58260271 | E19: =IF(OR(C19="",D19=""),"",ABS(C19-D19)) -> 0.0015002674 | F19: =T4_Correlated!F6 -> 0.03 | G19: =IF(D19="","Pending",IF(E19<=F19,"Pass","Fail")) -> Pass
A20: T09b | B20: Mean project duration | C20: =T4_Correlated!C7 -> 17.228616 | D20: =T4_Correlated!D7 -> 17.212537 | E20: =IF(OR(C20="",D20=""),"",ABS(C20-D20)) -> 0.016079178 | F20: =T4_Correlated!F7 -> 0.1 | G20: =IF(D20="","Pending",IF(E20<=F20,"Pass","Fail")) -> Pass
A21: T09c | B21: P80 project duration | C21: =T4_Correlated!C8 -> 18.580947 | D21: =T4_Correlated!D8 -> 18.530538 | E21: =IF(OR(C21="",D21=""),"",ABS(C21-D21)) -> 0.050408789 | F21: =T4_Correlated!F8 -> 0.15 | G21: =IF(D21="","Pending",IF(E21<=F21,"Pass","Fail")) -> Pass
A22: T21a | B22: Project duration (days) [current finance scenario] | C22: =Fin_CashFlow!B29 -> 700 | D22: =Fin_CashFlow!F29 -> 700 | E22: =IF(OR(C22="",D22=""),"",ABS(C22-D22)) -> 0 | F22: =Fin_CashFlow!H29 -> 0.0001 | G22: =IF(D22="","Pending",IF(E22<=F22,"Pass","Fail")) -> Pass
A23: T15a | B23: Construction cost incl. overheads (Rs lakh) [current finance scenario] | C23: =Fin_CashFlow!B30 -> 3777.85 | D23: =Fin_CashFlow!F30 -> 3777.85 | E23: =IF(OR(C23="",D23=""),"",ABS(C23-D23)) -> 0 | F23: =Fin_CashFlow!H30 -> 0.01 | G23: =IF(D23="","Pending",IF(E23<=F23,"Pass","Fail")) -> Pass
A24: T15 | B24: Project NPV (Rs lakh) [current finance scenario] | C24: =Fin_CashFlow!B31 -> 613.96567 | D24: =Fin_CashFlow!F31 -> 613.96567 | E24: =IF(OR(C24="",D24=""),"",ABS(C24-D24)) -> 0 | F24: =Fin_CashFlow!H31 -> 0.01 | G24: =IF(D24="","Pending",IF(E24<=F24,"Pass","Fail")) -> Pass
A25: T15b | B25: Equity NPV (Rs lakh) [current finance scenario] | C25: =Fin_CashFlow!B32 -> 313.48261 | D25: =Fin_CashFlow!F32 -> 313.48261 | E25: =IF(OR(C25="",D25=""),"",ABS(C25-D25)) -> 0 | F25: =Fin_CashFlow!H32 -> 0.01 | G25: =IF(D25="","Pending",IF(E25<=F25,"Pass","Fail")) -> Pass
A26: T16 | B26: Project IRR (annual) [current finance scenario] | C26: =Fin_CashFlow!B33 -> 0.19707914 | D26: =Fin_CashFlow!F33 -> 0.19707914 | E26: =IF(OR(C26="",D26=""),"",ABS(C26-D26)) -> 3.0808689e-15 | F26: =Fin_CashFlow!H33 -> 0.0001 | G26: =IF(D26="","Pending",IF(E26<=F26,"Pass","Fail")) -> Pass
A27: T16b | B27: Equity IRR (annual) [current finance scenario] | C27: =Fin_CashFlow!B34 -> 0.20619712 | D27: =Fin_CashFlow!F34 -> 0.20619712 | E27: =IF(OR(C27="",D27=""),"",ABS(C27-D27)) -> 0 | F27: =Fin_CashFlow!H34 -> 0.0001 | G27: =IF(D27="","Pending",IF(E27<=F27,"Pass","Fail")) -> Pass
A28: T18 | B28: Interest during construction (Rs lakh) [current finance scenario] | C28: =Fin_CashFlow!B35 -> 84.120813 | D28: =Fin_CashFlow!F35 -> 84.120813 | E28: =IF(OR(C28="",D28=""),"",ABS(C28-D28)) -> 0 | F28: =Fin_CashFlow!H35 -> 0.01 | G28: =IF(D28="","Pending",IF(E28<=F28,"Pass","Fail")) -> Pass
A29: T18b | B29: Total interest (Rs lakh) [current finance scenario] | C29: =Fin_CashFlow!B36 -> 94.176133 | D29: =Fin_CashFlow!F36 -> 94.176133 | E29: =IF(OR(C29="",D29=""),"",ABS(C29-D29)) -> 0 | F29: =Fin_CashFlow!H36 -> 0.01 | G29: =IF(D29="","Pending",IF(E29<=F29,"Pass","Fail")) -> Pass
A30: T19 | B30: Peak debt (Rs lakh) [current finance scenario] | C30: =Fin_CashFlow!B37 -> 842.61081 | D30: =Fin_CashFlow!F37 -> 842.61081 | E30: =IF(OR(C30="",D30=""),"",ABS(C30-D30)) -> 0 | F30: =Fin_CashFlow!H37 -> 0.01 | G30: =IF(D30="","Pending",IF(E30<=F30,"Pass","Fail")) -> Pass
A31: T21b | B31: Compensation to buyers (Rs lakh) [current finance scenario] | C31: =Fin_CashFlow!B38 -> 0 | D31: =Fin_CashFlow!F38 -> 0 | E31: =IF(OR(C31="",D31=""),"",ABS(C31-D31)) -> 0 | F31: =Fin_CashFlow!H38 -> 0.01 | G31: =IF(D31="","Pending",IF(E31<=F31,"Pass","Fail")) -> Pass
A32: T15c | B32: Undiscounted profit (Rs lakh) [current finance scenario] | C32: =Fin_CashFlow!B39 -> 1951.15 | D32: =Fin_CashFlow!F39 -> 1951.15 | E32: =IF(OR(C32="",D32=""),"",ABS(C32-D32)) -> 0 | F32: =Fin_CashFlow!H39 -> 0.01 | G32: =IF(D32="","Pending",IF(E32<=F32,"Pass","Fail")) -> Pass
B34: Pass | C34: =COUNTIF(G6:G32,"Pass") -> 27
B35: Fail | C35: =COUNTIF(G6:G32,"Fail") -> 0
B36: Pending | C36: =COUNTIF(G6:G32,"Pending") -> 0

Sheet T1_PERT
A1: T01: PERT means and simulated means (6-activity benchmark)
A2: PERT mean = (O + 4M + P)/6. Fill the yellow hand column from paper BEFORE looking at the Excel column.
A4: Activity | B4: Predecessors | C4: O (days) | D4: M (days) | E4: P (days) | F4: alpha | G4: beta | H4: PERT mean (Excel) | I4: SD (Excel) | J4: Your hand PERT mean | K4: Hand vs Excel | L4: Tool simulated mean | M4: Tool vs Excel | N4: Tolerance | O4: Result
A5: A | C5: 2 | D5: 4 | E5: 6 | F5: =1+4*(D5-C5)/(E5-C5) -> 3 | G5: =1+4*(E5-D5)/(E5-C5) -> 3 | H5: =(C5+4*D5+E5)/6 -> 4 | I5: =(E5-C5)/6 -> 0.66666667 | K5: =IF(J5="","",ABS(J5-H5)) | L5: 3.9985049 | M5: =IF(L5="","",ABS(L5-H5)) -> 0.0014951054 | N5: 0.02 | O5: =IF(L5="","Pending",IF(M5<=N5,"Pass","Fail")) -> Pass
A6: B | B6: A | C6: 3 | D6: 5 | E6: 9 | F6: =1+4*(D6-C6)/(E6-C6) -> 2.3333333 | G6: =1+4*(E6-D6)/(E6-C6) -> 3.6666667 | H6: =(C6+4*D6+E6)/6 -> 5.3333333 | I6: =(E6-C6)/6 -> 1 | K6: =IF(J6="","",ABS(J6-H6)) | L6: 5.3371195 | M6: =IF(L6="","",ABS(L6-H6)) -> 0.0037861225 | N6: 0.02 | O6: =IF(L6="","Pending",IF(M6<=N6,"Pass","Fail")) -> Pass
A7: C | B7: A | C7: 2 | D7: 6 | E7: 8 | F7: =1+4*(D7-C7)/(E7-C7) -> 3.6666667 | G7: =1+4*(E7-D7)/(E7-C7) -> 2.3333333 | H7: =(C7+4*D7+E7)/6 -> 5.6666667 | I7: =(E7-C7)/6 -> 1 | K7: =IF(J7="","",ABS(J7-H7)) | L7: 5.6652818 | M7: =IF(L7="","",ABS(L7-H7)) -> 0.0013848689 | N7: 0.02 | O7: =IF(L7="","Pending",IF(M7<=N7,"Pass","Fail")) -> Pass
A8: D | B8: B | C8: 4 | D8: 5 | E8: 8 | F8: =1+4*(D8-C8)/(E8-C8) -> 2 | G8: =1+4*(E8-D8)/(E8-C8) -> 4 | H8: =(C8+4*D8+E8)/6 -> 5.3333333 | I8: =(E8-C8)/6 -> 0.66666667 | K8: =IF(J8="","",ABS(J8-H8)) | L8: 5.334063 | M8: =IF(L8="","",ABS(L8-H8)) -> 0.00072968942 | N8: 0.02 | O8: =IF(L8="","Pending",IF(M8<=N8,"Pass","Fail")) -> Pass
A9: E | B9: C | C9: 3 | D9: 4 | E9: 7 | F9: =1+4*(D9-C9)/(E9-C9) -> 2 | G9: =1+4*(E9-D9)/(E9-C9) -> 4 | H9: =(C9+4*D9+E9)/6 -> 4.3333333 | I9: =(E9-C9)/6 -> 0.66666667 | K9: =IF(J9="","",ABS(J9-H9)) | L9: 4.3336108 | M9: =IF(L9="","",ABS(L9-H9)) -> 0.00027744782 | N9: 0.02 | O9: =IF(L9="","Pending",IF(M9<=N9,"Pass","Fail")) -> Pass
A10: F | B10: D;E | C10: 1 | D10: 2 | E10: 3 | F10: =1+4*(D10-C10)/(E10-C10) -> 3 | G10: =1+4*(E10-D10)/(E10-C10) -> 3 | H10: =(C10+4*D10+E10)/6 -> 2 | I10: =(E10-C10)/6 -> 0.33333333 | K10: =IF(J10="","",ABS(J10-H10)) | L10: 2.0001043 | M10: =IF(L10="","",ABS(L10-H10)) -> 0.00010426561 | N10: 0.02 | O10: =IF(L10="","Pending",IF(M10<=N10,"Pass","Fail")) -> Pass
A12: Tool values: 200,000 iterations, seed 42, from scripts/export_validation_values.py.

Sheet T2_CPM
A1: T02-T03: Critical path by hand (forward and backward pass)
A2: Network: A first; B then D, and C then E, run in parallel; F needs both D and E.
A4: Most-likely durations
A5: Activity | B5: Duration | C5: ES | D5: EF | E5: LS | F5: LF | G5: Float | H5: Critical?
A6: A | B6: =T1_PERT!D5 -> 4 | C6: =0 -> 0 | D6: =C6+B6 -> 4 | E6: =F6-B6 -> 0 | F6: =MIN(E7,E8) -> 4 | G6: =E6-C6 -> 0 | H6: =IF(ABS(G6)<0.000001,"Yes","No") -> Yes
A7: B | B7: =T1_PERT!D6 -> 5 | C7: =D6 -> 4 | D7: =C7+B7 -> 9 | E7: =F7-B7 -> 4 | F7: =E9 -> 9 | G7: =E7-C7 -> 0 | H7: =IF(ABS(G7)<0.000001,"Yes","No") -> Yes
A8: C | B8: =T1_PERT!D7 -> 6 | C8: =D6 -> 4 | D8: =C8+B8 -> 10 | E8: =F8-B8 -> 4 | F8: =E10 -> 10 | G8: =E8-C8 -> 0 | H8: =IF(ABS(G8)<0.000001,"Yes","No") -> Yes
A9: D | B9: =T1_PERT!D8 -> 5 | C9: =D7 -> 9 | D9: =C9+B9 -> 14 | E9: =F9-B9 -> 9 | F9: =E11 -> 14 | G9: =E9-C9 -> 0 | H9: =IF(ABS(G9)<0.000001,"Yes","No") -> Yes
A10: E | B10: =T1_PERT!D9 -> 4 | C10: =D8 -> 10 | D10: =C10+B10 -> 14 | E10: =F10-B10 -> 10 | F10: =E11 -> 14 | G10: =E10-C10 -> 0 | H10: =IF(ABS(G10)<0.000001,"Yes","No") -> Yes
A11: F | B11: =T1_PERT!D10 -> 2 | C11: =MAX(D9,D10) -> 14 | D11: =C11+B11 -> 16 | E11: =F11-B11 -> 14 | F11: =D11 -> 16 | G11: =E11-C11 -> 0 | H11: =IF(ABS(G11)<0.000001,"Yes","No") -> Yes
A14: PERT mean durations
A15: Activity | B15: Duration | C15: ES | D15: EF | E15: LS | F15: LF | G15: Float | H15: Critical?
A16: A | B16: =T1_PERT!H5 -> 4 | C16: =0 -> 0 | D16: =C16+B16 -> 4 | E16: =F16-B16 -> 0 | F16: =MIN(E17,E18) -> 4 | G16: =E16-C16 -> 0 | H16: =IF(ABS(G16)<0.000001,"Yes","No") -> Yes
A17: B | B17: =T1_PERT!H6 -> 5.3333333 | C17: =D16 -> 4 | D17: =C17+B17 -> 9.3333333 | E17: =F17-B17 -> 4 | F17: =E19 -> 9.3333333 | G17: =E17-C17 -> 0 | H17: =IF(ABS(G17)<0.000001,"Yes","No") -> Yes
A18: C | B18: =T1_PERT!H7 -> 5.6666667 | C18: =D16 -> 4 | D18: =C18+B18 -> 9.6666667 | E18: =F18-B18 -> 4.6666667 | F18: =E20 -> 10.333333 | G18: =E18-C18 -> 0.66666667 | H18: =IF(ABS(G18)<0.000001,"Yes","No") -> No
A19: D | B19: =T1_PERT!H8 -> 5.3333333 | C19: =D17 -> 9.3333333 | D19: =C19+B19 -> 14.666667 | E19: =F19-B19 -> 9.3333333 | F19: =E21 -> 14.666667 | G19: =E19-C19 -> 0 | H19: =IF(ABS(G19)<0.000001,"Yes","No") -> Yes
A20: E | B20: =T1_PERT!H9 -> 4.3333333 | C20: =D18 -> 9.6666667 | D20: =C20+B20 -> 14 | E20: =F20-B20 -> 10.333333 | F20: =E21 -> 14.666667 | G20: =E20-C20 -> 0.66666667 | H20: =IF(ABS(G20)<0.000001,"Yes","No") -> No
A21: F | B21: =T1_PERT!H10 -> 2 | C21: =MAX(D19,D20) -> 14.666667 | D21: =C21+B21 -> 16.666667 | E21: =F21-B21 -> 14.666667 | F21: =D21 -> 16.666667 | G21: =E21-C21 -> 0 | H21: =IF(ABS(G21)<0.000001,"Yes","No") -> Yes
A25: Checks
A26: Test | B26: What | C26: Excel | D26: Your hand value | E26: Tool value | F26: Tolerance | G26: Hand vs Excel | H26: Result
A27: T02 | B27: Project duration, most-likely (days) | C27: =D11 -> 16 | E27: 16 | F27: 0.001 | G27: =IF(D27="","",ABS(D27-C27)) | H27: =IF(E27="","Pending",IF(ABS(E27-C27)<=F27,"Pass","Fail")) -> Pass
A28: T03 | B28: Project duration, PERT on one critical path (days) | C28: =D21 -> 16.666667 | E28: 16.666667 | F28: 0.001 | G28: =IF(D28="","",ABS(D28-C28)) | H28: =IF(E28="","Pending",IF(ABS(E28-C28)<=F28,"Pass","Fail")) -> Pass
A30: With most-likely values both paths take 16 days, so every activity is critical. With PERT means, path A-B-D-F is longer. The simulation mean (T3) is higher than both: that gap is merge bias.

Sheet T3_MonteCarlo
A1: T04-T06: Monte Carlo in plain Excel (5,000 runs, activities independent)
A2: Each row is one run: BETAINV(RAND(), alpha, beta, O, P) per activity. Press F9 to re-run.
A4: Test | B4: Measure | C4: Excel (5,000 runs) | D4: Tool (200,000 runs) | E4: Difference | F4: Tolerance | G4: Result
A5: T04 | B5: Mean project duration | C5: =AVERAGE(J20:J5019) -> 17.120653 | D5: 17.122409 | E5: =ABS(C5-D5) -> 0.0017561564 | F5: 0.1 | G5: =IF(D5="","Pending",IF(E5<=F5,"Pass","Fail")) -> Pass
A6: T05b | B6: P50 project duration | C6: =PERCENTILE(J20:J5019,0.5) -> 17.11695 | D6: 17.098149 | E6: =ABS(C6-D6) -> 0.018800633 | F6: 0.15 | G6: =IF(D6="","Pending",IF(E6<=F6,"Pass","Fail")) -> Pass
A7: T05 | B7: P80 project duration | C7: =PERCENTILE(J20:J5019,0.8) -> 18.301044 | D7: 18.308138 | E7: =ABS(C7-D7) -> 0.0070937073 | F7: 0.15 | G7: =IF(D7="","Pending",IF(E7<=F7,"Pass","Fail")) -> Pass
A8: T05c | B8: P90 project duration | C8: =PERCENTILE(J20:J5019,0.9) -> 18.949934 | D8: 18.944659 | E8: =ABS(C8-D8) -> 0.0052750866 | F8: 0.2 | G8: =IF(D8="","Pending",IF(E8<=F8,"Pass","Fail")) -> Pass
A9: T06 | B9: Criticality index of B (share of runs A-B-D-F is longest) | C9: =AVERAGE(K20:K5019) -> 0.6322 | D9: 0.63011 | E9: =ABS(C9-D9) -> 0.00209 | F9: 0.03 | G9: =IF(D9="","Pending",IF(E9<=F9,"Pass","Fail")) -> Pass
B11: Standard deviation of project duration | C11: =STDEV(J20:J5019) -> 1.3982029 | E11: Excel mean of each activity vs PERT mean (extra check): | H11: Columns F and G should agree within about 0.05
B12: Standard error of the Excel mean | C12: =C11/SQRT(5000) -> 0.019773575 | E12: A | F12: =AVERAGE(B20:B5019) -> 3.9998955 | G12: =T1_PERT!H5 -> 4
B13: PERT single-path answer (T2) | C13: =T2_CPM!D21 -> 16.666667 | E13: B | F13: =AVERAGE(C20:C5019) -> 5.3410528 | G13: =T1_PERT!H6 -> 5.3333333
B14: Merge bias: simulated mean minus PERT | C14: =C5-C13 -> 0.45398589 | E14: C | F14: =AVERAGE(D20:D5019) -> 5.6894908 | G14: =T1_PERT!H7 -> 5.6666667
E15: D | F15: =AVERAGE(E20:E5019) -> 5.3383601 | G15: =T1_PERT!H8 -> 5.3333333
E16: E | F16: =AVERAGE(F20:F5019) -> 4.323717 | G16: =T1_PERT!H9 -> 4.3333333
E17: F | F17: =AVERAGE(G20:G5019) -> 1.9961432 | G17: =T1_PERT!H10 -> 2
A19: Run | B19: A | C19: B | D19: C | E19: D | F19: E | G19: F | H19: Path A-B-D-F | I19: Path A-C-E-F | J19: Project | K19: B critical (1/0)
A20: 1 | B20: =BETAINV(RAND(),T1_PERT!$F$5,T1_PERT!$G$5,T1_PERT!$C$5,T1_PERT!$E$5) -> 3.4988599 | C20: =BETAINV(RAND(),T1_PERT!$F$6,T1_PERT!$G$6,T1_PERT!$C$6,T1_PERT!$E$6) -> 4.3525915 | D20: =BETAINV(RAND(),T1_PERT!$F$7,T1_PERT!$G$7,T1_PERT!$C$7,T1_PERT!$E$7) -> 5.0992542 | E20: =BETAINV(RAND(),T1_PERT!$F$8,T1_PERT!$G$8,T1_PERT!$C$8,T1_PERT!$E$8) -> 5.1030156 | F20: =BETAINV(RAND(),T1_PERT!$F$9,T1_PERT!$G$9,T1_PERT!$C$9,T1_PERT!$E$9) -> 4.6344433 | G20: =BETAINV(RAND(),T1_PERT!$F$10,T1_PERT!$G$10,T1_PERT!$C$10,T1_PERT!$E$10) -> 1.9398549 | H20: =B20+C20+E20+G20 -> 14.894322 | I20: =B20+D20+F20+G20 -> 15.172412 | J20: =MAX(H20,I20) -> 15.172412 | K20: =IF(H20>=I20,1,0) -> 0
A21: 2 | B21: =BETAINV(RAND(),T1_PERT!$F$5,T1_PERT!$G$5,T1_PERT!$C$5,T1_PERT!$E$5) -> 3.6312938 | C21: =BETAINV(RAND(),T1_PERT!$F$6,T1_PERT!$G$6,T1_PERT!$C$6,T1_PERT!$E$6) -> 3.7994455 | D21: =BETAINV(RAND(),T1_PERT!$F$7,T1_PERT!$G$7,T1_PERT!$C$7,T1_PERT!$E$7) -> 3.1343584 | E21: =BETAINV(RAND(),T1_PERT!$F$8,T1_PERT!$G$8,T1_PERT!$C$8,T1_PERT!$E$8) -> 5.8341348 | F21: =BETAINV(RAND(),T1_PERT!$F$9,T1_PERT!$G$9,T1_PERT!$C$9,T1_PERT!$E$9) -> 5.7597805 | G21: =BETAINV(RAND(),T1_PERT!$F$10,T1_PERT!$G$10,T1_PERT!$C$10,T1_PERT!$E$10) -> 1.9618799 | H21: =B21+C21+E21+G21 -> 15.226754 | I21: =B21+D21+F21+G21 -> 14.487313 | J21: =MAX(H21,I21) -> 15.226754 | K21: =IF(H21>=I21,1,0) -> 1
A22: 3 | B22: =BETAINV(RAND(),T1_PERT!$F$5,T1_PERT!$G$5,T1_PERT!$C$5,T1_PERT!$E$5) -> 3.7679128 | C22: =BETAINV(RAND(),T1_PERT!$F$6,T1_PERT!$G$6,T1_PERT!$C$6,T1_PERT!$E$6) -> 5.9882017 | D22: =BETAINV(RAND(),T1_PERT!$F$7,T1_PERT!$G$7,T1_PERT!$C$7,T1_PERT!$E$7) -> 6.6829431 | E22: =BETAINV(RAND(),T1_PERT!$F$8,T1_PERT!$G$8,T1_PERT!$C$8,T1_PERT!$E$8) -> 4.3203686 | F22: =BETAINV(RAND(),T1_PERT!$F$9,T1_PERT!$G$9,T1_PERT!$C$9,T1_PERT!$E$9) -> 4.8519574 | G22: =BETAINV(RAND(),T1_PERT!$F$10,T1_PERT!$G$10,T1_PERT!$C$10,T1_PERT!$E$10) -> 2.2694327 | H22: =B22+C22+E22+G22 -> 16.345916 | I22: =B22+D22+F22+G22 -> 17.572246 | J22: =MAX(H22,I22) -> 17.572246 | K22: =IF(H22>=I22,1,0) -> 0
A23: 4 | B23: =BETAINV(RAND(),T1_PERT!$F$5,T1_PERT!$G$5,T1_PERT!$C$5,T1_PERT!$E$5) -> 4.2957159 | C23: =BETAINV(RAND(),T1_PERT!$F$6,T1_PERT!$G$6,T1_PERT!$C$6,T1_PERT!$E$6) -> 5.0409841 | D23: =BETAINV(RAND(),T1_PERT!$F$7,T1_PERT!$G$7,T1_PERT!$C$7,T1_PERT!$E$7) -> 4.5588679 | E23: =BETAINV(RAND(),T1_PERT!$F$8,T1_PERT!$G$8,T1_PERT!$C$8,T1_PERT!$E$8) -> 4.5742977 | F23: =BETAINV(RAND(),T1_PERT!$F$9,T1_PERT!$G$9,T1_PERT!$C$9,T1_PERT!$E$9) -> 5.3100171 | G23: =BETAINV(RAND(),T1_PERT!$F$10,T1_PERT!$G$10,T1_PERT!$C$10,T1_PERT!$E$10) -> 2.0228148 | H23: =B23+C23+E23+G23 -> 15.933812 | I23: =B23+D23+F23+G23 -> 16.187416 | J23: =MAX(H23,I23) -> 16.187416 | K23: =IF(H23>=I23,1,0) -> 0
A24: 5 | B24: =BETAINV(RAND(),T1_PERT!$F$5,T1_PERT!$G$5,T1_PERT!$C$5,T1_PERT!$E$5) -> 4.4224655 | C24: =BETAINV(RAND(),T1_PERT!$F$6,T1_PERT!$G$6,T1_PERT!$C$6,T1_PERT!$E$6) -> 6.2329921 | D24: =BETAINV(RAND(),T1_PERT!$F$7,T1_PERT!$G$7,T1_PERT!$C$7,T1_PERT!$E$7) -> 7.7115833 | E24: =BETAINV(RAND(),T1_PERT!$F$8,T1_PERT!$G$8,T1_PERT!$C$8,T1_PERT!$E$8) -> 5.5373093 | F24: =BETAINV(RAND(),T1_PERT!$F$9,T1_PERT!$G$9,T1_PERT!$C$9,T1_PERT!$E$9) -> 4.2061783 | G24: =BETAINV(RAND(),T1_PERT!$F$10,T1_PERT!$G$10,T1_PERT!$C$10,T1_PERT!$E$10) -> 2.6916301 | H24: =B24+C24+E24+G24 -> 18.884397 | I24: =B24+D24+F24+G24 -> 19.031857 | J24: =MAX(H24,I24) -> 19.031857 | K24: =IF(H24>=I24,1,0) -> 0
A25: 6 | B25: =BETAINV(RAND(),T1_PERT!$F$5,T1_PERT!$G$5,T1_PERT!$C$5,T1_PERT!$E$5) -> 4.4388757 | C25: =BETAINV(RAND(),T1_PERT!$F$6,T1_PERT!$G$6,T1_PERT!$C$6,T1_PERT!$E$6) -> 4.4808404 | D25: =BETAINV(RAND(),T1_PERT!$F$7,T1_PERT!$G$7,T1_PERT!$C$7,T1_PERT!$E$7) -> 7.0050511 | E25: =BETAINV(RAND(),T1_PERT!$F$8,T1_PERT!$G$8,T1_PERT!$C$8,T1_PERT!$E$8) -> 5.8753055 | F25: =BETAINV(RAND(),T1_PERT!$F$9,T1_PERT!$G$9,T1_PERT!$C$9,T1_PERT!$E$9) -> 4.3613245 | G25: =BETAINV(RAND(),T1_PERT!$F$10,T1_PERT!$G$10,T1_PERT!$C$10,T1_PERT!$E$10) -> 1.7030549 | H25: =B25+C25+E25+G25 -> 16.498077 | I25: =B25+D25+F25+G25 -> 17.508306 | J25: =MAX(H25,I25) -> 17.508306 | K25: =IF(H25>=I25,1,0) -> 0
A26: 7 | B26: =BETAINV(RAND(),T1_PERT!$F$5,T1_PERT!$G$5,T1_PERT!$C$5,T1_PERT!$E$5) -> 3.8198131 | C26: =BETAINV(RAND(),T1_PERT!$F$6,T1_PERT!$G$6,T1_PERT!$C$6,T1_PERT!$E$6) -> 3.2581801 | D26: =BETAINV(RAND(),T1_PERT!$F$7,T1_PERT!$G$7,T1_PERT!$C$7,T1_PERT!$E$7) -> 3.7661506 | E26: =BETAINV(RAND(),T1_PERT!$F$8,T1_PERT!$G$8,T1_PERT!$C$8,T1_PERT!$E$8) -> 4.6593406 | F26: =BETAINV(RAND(),T1_PERT!$F$9,T1_PERT!$G$9,T1_PERT!$C$9,T1_PERT!$E$9) -> 4.1079725 | G26: =BETAINV(RAND(),T1_PERT!$F$10,T1_PERT!$G$10,T1_PERT!$C$10,T1_PERT!$E$10) -> 2.0284499 | H26: =B26+C26+E26+G26 -> 13.765784 | I26: =B26+D26+F26+G26 -> 13.722386 | J26: =MAX(H26,I26) -> 13.765784 | K26: =IF(H26>=I26,1,0) -> 1
A27: 8 | B27: =BETAINV(RAND(),T1_PERT!$F$5,T1_PERT!$G$5,T1_PERT!$C$5,T1_PERT!$E$5) -> 4.3407747 | C27: =BETAINV(RAND(),T1_PERT!$F$6,T1_PERT!$G$6,T1_PERT!$C$6,T1_PERT!$E$6) -> 4.3871173 | D27: =BETAINV(RAND(),T1_PERT!$F$7,T1_PERT!$G$7,T1_PERT!$C$7,T1_PERT!$E$7) -> 3.7426146 | E27: =BETAINV(RAND(),T1_PERT!$F$8,T1_PERT!$G$8,T1_PERT!$C$8,T1_PERT!$E$8) -> 5.6688456 | F27: =BETAINV(RAND(),T1_PERT!$F$9,T1_PERT!$G$9,T1_PERT!$C$9,T1_PERT!$E$9) -> 3.6857324 | G27: =BETAINV(RAND(),T1_PERT!$F$10,T1_PERT!$G$10,T1_PERT!$C$10,T1_PERT!$E$10) -> 1.8602413 | H27: =B27+C27+E27+G27 -> 16.256979 | I27: =B27+D27+F27+G27 -> 13.629363 | J27: =MAX(H27,I27) -> 16.256979 | K27: =IF(H27>=I27,1,0) -> 1
A28: 9 | B28: =BETAINV(RAND(),T1_PERT!$F$5,T1_PERT!$G$5,T1_PERT!$C$5,T1_PERT!$E$5) -> 3.0959509 | C28: =BETAINV(RAND(),T1_PERT!$F$6,T1_PERT!$G$6,T1_PERT!$C$6,T1_PERT!$E$6) -> 6.755576 | D28: =BETAINV(RAND(),T1_PERT!$F$7,T1_PERT!$G$7,T1_PERT!$C$7,T1_PERT!$E$7) -> 4.8128772 | E28: =BETAINV(RAND(),T1_PERT!$F$8,T1_PERT!$G$8,T1_PERT!$C$8,T1_PERT!$E$8) -> 4.9207861 | F28: =BETAINV(RAND(),T1_PERT!$F$9,T1_PERT!$G$9,T1_PERT!$C$9,T1_PERT!$E$9) -> 5.1955895 | G28: =BETAINV(RAND(),T1_PERT!$F$10,T1_PERT!$G$10,T1_PERT!$C$10,T1_PERT!$E$10) -> 2.0424345 | H28: =B28+C28+E28+G28 -> 16.814747 | I28: =B28+D28+F28+G28 -> 15.146852 | J28: =MAX(H28,I28) -> 16.814747 | K28: =IF(H28>=I28,1,0) -> 1
A29: 10 | B29: =BETAINV(RAND(),T1_PERT!$F$5,T1_PERT!$G$5,T1_PERT!$C$5,T1_PERT!$E$5) -> 3.920724 | C29: =BETAINV(RAND(),T1_PERT!$F$6,T1_PERT!$G$6,T1_PERT!$C$6,T1_PERT!$E$6) -> 3.9056227 | D29: =BETAINV(RAND(),T1_PERT!$F$7,T1_PERT!$G$7,T1_PERT!$C$7,T1_PERT!$E$7) -> 4.0705783 | E29: =BETAINV(RAND(),T1_PERT!$F$8,T1_PERT!$G$8,T1_PERT!$C$8,T1_PERT!$E$8) -> 5.8147626 | F29: =BETAINV(RAND(),T1_PERT!$F$9,T1_PERT!$G$9,T1_PERT!$C$9,T1_PERT!$E$9) -> 4.7993646 | G29: =BETAINV(RAND(),T1_PERT!$F$10,T1_PERT!$G$10,T1_PERT!$C$10,T1_PERT!$E$10) -> 2.5553083 | H29: =B29+C29+E29+G29 -> 16.196418 | I29: =B29+D29+F29+G29 -> 15.345975 | J29: =MAX(H29,I29) -> 16.196418 | K29: =IF(H29>=I29,1,0) -> 1
A30: 11 | B30: =BETAINV(RAND(),T1_PERT!$F$5,T1_PERT!$G$5,T1_PERT!$C$5,T1_PERT!$E$5) -> 4.0763474 | C30: =BETAINV(RAND(),T1_PERT!$F$6,T1_PERT!$G$6,T1_PERT!$C$6,T1_PERT!$E$6) -> 6.3417108 | D30: =BETAINV(RAND(),T1_PERT!$F$7,T1_PERT!$G$7,T1_PERT!$C$7,T1_PERT!$E$7) -> 3.0366352 | E30: =BETAINV(RAND(),T1_PERT!$F$8,T1_PERT!$G$8,T1_PERT!$C$8,T1_PERT!$E$8) -> 5.8228149 | F30: =BETAINV(RAND(),T1_PERT!$F$9,T1_PERT!$G$9,T1_PERT!$C$9,T1_PERT!$E$9) -> 4.041543 | G30: =BETAINV(RAND(),T1_PERT!$F$10,T1_PERT!$G$10,T1_PERT!$C$10,T1_PERT!$E$10) -> 1.9332313 | H30: =B30+C30+E30+G30 -> 18.174104 | I30: =B30+D30+F30+G30 -> 13.087757 | J30: =MAX(H30,I30) -> 18.174104 | K30: =IF(H30>=I30,1,0) -> 1
A31: 12 | B31: =BETAINV(RAND(),T1_PERT!$F$5,T1_PERT!$G$5,T1_PERT!$C$5,T1_PERT!$E$5) -> 5.1106987 | C31: =BETAINV(RAND(),T1_PERT!$F$6,T1_PERT!$G$6,T1_PERT!$C$6,T1_PERT!$E$6) -> 4.6753793 | D31: =BETAINV(RAND(),T1_PERT!$F$7,T1_PERT!$G$7,T1_PERT!$C$7,T1_PERT!$E$7) -> 3.9562263 | E31: =BETAINV(RAND(),T1_PERT!$F$8,T1_PERT!$G$8,T1_PERT!$C$8,T1_PERT!$E$8) -> 5.1580089 | F31: =BETAINV(RAND(),T1_PERT!$F$9,T1_PERT!$G$9,T1_PERT!$C$9,T1_PERT!$E$9) -> 4.7302714 | G31: =BETAINV(RAND(),T1_PERT!$F$10,T1_PERT!$G$10,T1_PERT!$C$10,T1_PERT!$E$10) -> 2.5686076 | H31: =B31+C31+E31+G31 -> 17.512695 | I31: =B31+D31+F31+G31 -> 16.365804 | J31: =MAX(H31,I31) -> 17.512695 | K31: =IF(H31>=I31,1,0) -> 1
... A5019: 5000 | B5019: =BETAINV(RAND(),T1_PERT!$F$5,T1_PERT!$G$5,T1_PERT!$C$5,T1_PERT!$E$5) -> 4.750293 | C5019: =BETAINV(RAND(),T1_PERT!$F$6,T1_PERT!$G$6,T1_PERT!$C$6,T1_PERT!$E$6) -> 5.0101489 | D5019: =BETAINV(RAND(),T1_PERT!$F$7,T1_PERT!$G$7,T1_PERT!$C$7,T1_PERT!$E$7) -> 4.7322718 | E5019: =BETAINV(RAND(),T1_PERT!$F$8,T1_PERT!$G$8,T1_PERT!$C$8,T1_PERT!$E$8) -> 4.7956863 | F5019: =BETAINV(RAND(),T1_PERT!$F$9,T1_PERT!$G$9,T1_PERT!$C$9,T1_PERT!$E$9) -> 5.6203176 | G5019: =BETAINV(RAND(),T1_PERT!$F$10,T1_PERT!$G$10,T1_PERT!$C$10,T1_PERT!$E$10) -> 2.0373835 | H5019: =B5019+C5019+E5019+G5019 -> 16.593512 | I5019: =B5019+D5019+F5019+G5019 -> 17.140266 | J5019: =MAX(H5019,I5019) -> 17.140266 | K5019: =IF(H5019>=I5019,1,0) -> 0

Sheet T4_Correlated
A1: T09: Correlation check (optional): B and D correlated, hand-built Cholesky step
A2: z1 = NORMSINV(RAND()); z2 = rho*z1 + SQRT(1-rho^2)*NORMSINV(RAND()); u = NORMSDIST(z); duration = BETAINV(u, ...). Other activities independent.
B4: Correlation rho (B with D) | C4: 0.6
A5: Test | B5: Measure | C5: Excel | D5: Tool | E5: Difference | F5: Tolerance | G5: Result
A6: T09 | B6: Rank correlation of B and D (CORREL of their uniforms) | C6: =CORREL(D20:D5019,E20:E5019) -> 0.58410298 | D6: 0.58260271 | E6: =ABS(C6-D6) -> 0.0015002674 | F6: 0.03 | G6: =IF(D6="","Pending",IF(E6<=F6,"Pass","Fail")) -> Pass
A7: T09b | B7: Mean project duration | C7: =AVERAGE(N20:N5019) -> 17.228616 | D7: 17.212537 | E7: =ABS(C7-D7) -> 0.016079178 | F7: 0.1 | G7: =IF(D7="","Pending",IF(E7<=F7,"Pass","Fail")) -> Pass
A8: T09c | B8: P80 project duration | C8: =PERCENTILE(N20:N5019,0.8) -> 18.580947 | D8: 18.530538 | E8: =ABS(C8-D8) -> 0.050408789 | F8: 0.15 | G8: =IF(D8="","Pending",IF(E8<=F8,"Pass","Fail")) -> Pass
B10: Theory: (6/pi) x asin(rho/2) | C10: =6/PI()*ASIN(C4/2) -> 0.5819201
B11: P80 with B, D independent (from T3) | C11: =T3_MonteCarlo!C7 -> 18.301044
B12: Effect of correlation on P80 (days) | C12: =C8-C11 -> 0.27990231
B13: B and D are on the same path, so correlating them widens the spread and raises P80.
A19: Run | B19: z1 | C19: z2 | D19: u for B | E19: u for D | F19: A | G19: B | H19: C | I19: D | J19: E | K19: F | L19: Path A-B-D-F | M19: Path A-C-E-F | N19: Project
A20: 1 | B20: =NORMSINV(RAND()) -> 1.3123346 | C20: =$C$4*B20+SQRT(1-$C$4^2)*NORMSINV(RAND()) -> 1.2843138 | D20: =NORMSDIST(B20) -> 0.90529637 | E20: =NORMSDIST(C20) -> 0.90048392 | F20: =BETAINV(RAND(),T1_PERT!$F$5,T1_PERT!$G$5,T1_PERT!$C$5,T1_PERT!$E$5) -> 3.1684807 | G20: =BETAINV(D20,T1_PERT!$F$6,T1_PERT!$G$6,T1_PERT!$C$6,T1_PERT!$E$6) -> 6.9031605 | H20: =BETAINV(RAND(),T1_PERT!$F$7,T1_PERT!$G$7,T1_PERT!$C$7,T1_PERT!$E$7) -> 3.6380273 | I20: =BETAINV(E20,T1_PERT!$F$8,T1_PERT!$G$8,T1_PERT!$C$8,T1_PERT!$E$8) -> 6.3378658 | J20: =BETAINV(RAND(),T1_PERT!$F$9,T1_PERT!$G$9,T1_PERT!$C$9,T1_PERT!$E$9) -> 5.4687774 | K20: =BETAINV(RAND(),T1_PERT!$F$10,T1_PERT!$G$10,T1_PERT!$C$10,T1_PERT!$E$10) -> 1.3234595 | L20: =F20+G20+I20+K20 -> 17.732966 | M20: =F20+H20+J20+K20 -> 13.598745 | N20: =MAX(L20,M20) -> 17.732966
A21: 2 | B21: =NORMSINV(RAND()) -> -0.1710861 | C21: =$C$4*B21+SQRT(1-$C$4^2)*NORMSINV(RAND()) -> -0.91637937 | D21: =NORMSDIST(B21) -> 0.43207803 | E21: =NORMSDIST(C21) -> 0.17973398 | F21: =BETAINV(RAND(),T1_PERT!$F$5,T1_PERT!$G$5,T1_PERT!$C$5,T1_PERT!$E$5) -> 4.1003041 | G21: =BETAINV(D21,T1_PERT!$F$6,T1_PERT!$G$6,T1_PERT!$C$6,T1_PERT!$E$6) -> 5.0465915 | H21: =BETAINV(RAND(),T1_PERT!$F$7,T1_PERT!$G$7,T1_PERT!$C$7,T1_PERT!$E$7) -> 5.4292712 | I21: =BETAINV(E21,T1_PERT!$F$8,T1_PERT!$G$8,T1_PERT!$C$8,T1_PERT!$E$8) -> 4.6320553 | J21: =BETAINV(RAND(),T1_PERT!$F$9,T1_PERT!$G$9,T1_PERT!$C$9,T1_PERT!$E$9) -> 5.1356318 | K21: =BETAINV(RAND(),T1_PERT!$F$10,T1_PERT!$G$10,T1_PERT!$C$10,T1_PERT!$E$10) -> 1.9904915 | L21: =F21+G21+I21+K21 -> 15.769442 | M21: =F21+H21+J21+K21 -> 16.655699 | N21: =MAX(L21,M21) -> 16.655699
A22: 3 | B22: =NORMSINV(RAND()) -> -1.8992084 | C22: =$C$4*B22+SQRT(1-$C$4^2)*NORMSINV(RAND()) -> -0.42947191 | D22: =NORMSDIST(B22) -> 0.028768539 | E22: =NORMSDIST(C22) -> 0.33378992 | F22: =BETAINV(RAND(),T1_PERT!$F$5,T1_PERT!$G$5,T1_PERT!$C$5,T1_PERT!$E$5) -> 4.634623 | G22: =BETAINV(D22,T1_PERT!$F$6,T1_PERT!$G$6,T1_PERT!$C$6,T1_PERT!$E$6) -> 3.507599 | H22: =BETAINV(RAND(),T1_PERT!$F$7,T1_PERT!$G$7,T1_PERT!$C$7,T1_PERT!$E$7) -> 5.0935758 | I22: =BETAINV(E22,T1_PERT!$F$8,T1_PERT!$G$8,T1_PERT!$C$8,T1_PERT!$E$8) -> 4.9366105 | J22: =BETAINV(RAND(),T1_PERT!$F$9,T1_PERT!$G$9,T1_PERT!$C$9,T1_PERT!$E$9) -> 4.5701236 | K22: =BETAINV(RAND(),T1_PERT!$F$10,T1_PERT!$G$10,T1_PERT!$C$10,T1_PERT!$E$10) -> 1.6822853 | L22: =F22+G22+I22+K22 -> 14.761118 | M22: =F22+H22+J22+K22 -> 15.980608 | N22: =MAX(L22,M22) -> 15.980608
A23: 4 | B23: =NORMSINV(RAND()) -> -0.32092334 | C23: =$C$4*B23+SQRT(1-$C$4^2)*NORMSINV(RAND()) -> -2.3047474 | D23: =NORMSDIST(B23) -> 0.37413424 | E23: =NORMSDIST(C23) -> 0.010590362 | F23: =BETAINV(RAND(),T1_PERT!$F$5,T1_PERT!$G$5,T1_PERT!$C$5,T1_PERT!$E$5) -> 2.5542256 | G23: =BETAINV(D23,T1_PERT!$F$6,T1_PERT!$G$6,T1_PERT!$C$6,T1_PERT!$E$6) -> 4.8698422 | H23: =BETAINV(RAND(),T1_PERT!$F$7,T1_PERT!$G$7,T1_PERT!$C$7,T1_PERT!$E$7) -> 5.110406 | I23: =BETAINV(E23,T1_PERT!$F$8,T1_PERT!$G$8,T1_PERT!$C$8,T1_PERT!$E$8) -> 4.1346667 | J23: =BETAINV(RAND(),T1_PERT!$F$9,T1_PERT!$G$9,T1_PERT!$C$9,T1_PERT!$E$9) -> 5.3505907 | K23: =BETAINV(RAND(),T1_PERT!$F$10,T1_PERT!$G$10,T1_PERT!$C$10,T1_PERT!$E$10) -> 2.0561551 | L23: =F23+G23+I23+K23 -> 13.61489 | M23: =F23+H23+J23+K23 -> 15.071377 | N23: =MAX(L23,M23) -> 15.071377
A24: 5 | B24: =NORMSINV(RAND()) -> 0.0034737609 | C24: =$C$4*B24+SQRT(1-$C$4^2)*NORMSINV(RAND()) -> -0.25177159 | D24: =NORMSDIST(B24) -> 0.50138583 | E24: =NORMSDIST(C24) -> 0.40060881 | F24: =BETAINV(RAND(),T1_PERT!$F$5,T1_PERT!$G$5,T1_PERT!$C$5,T1_PERT!$E$5) -> 3.8714177 | G24: =BETAINV(D24,T1_PERT!$F$6,T1_PERT!$G$6,T1_PERT!$C$6,T1_PERT!$E$6) -> 5.2591653 | H24: =BETAINV(RAND(),T1_PERT!$F$7,T1_PERT!$G$7,T1_PERT!$C$7,T1_PERT!$E$7) -> 5.2440936 | I24: =BETAINV(E24,T1_PERT!$F$8,T1_PERT!$G$8,T1_PERT!$C$8,T1_PERT!$E$8) -> 5.0634322 | J24: =BETAINV(RAND(),T1_PERT!$F$9,T1_PERT!$G$9,T1_PERT!$C$9,T1_PERT!$E$9) -> 4.9116978 | K24: =BETAINV(RAND(),T1_PERT!$F$10,T1_PERT!$G$10,T1_PERT!$C$10,T1_PERT!$E$10) -> 1.8665049 | L24: =F24+G24+I24+K24 -> 16.06052 | M24: =F24+H24+J24+K24 -> 15.893714 | N24: =MAX(L24,M24) -> 16.06052
A25: 6 | B25: =NORMSINV(RAND()) -> -1.0273882 | C25: =$C$4*B25+SQRT(1-$C$4^2)*NORMSINV(RAND()) -> -1.1695216 | D25: =NORMSDIST(B25) -> 0.15211885 | E25: =NORMSDIST(C25) -> 0.12109678 | F25: =BETAINV(RAND(),T1_PERT!$F$5,T1_PERT!$G$5,T1_PERT!$C$5,T1_PERT!$E$5) -> 3.8729602 | G25: =BETAINV(D25,T1_PERT!$F$6,T1_PERT!$G$6,T1_PERT!$C$6,T1_PERT!$E$6) -> 4.1346952 | H25: =BETAINV(RAND(),T1_PERT!$F$7,T1_PERT!$G$7,T1_PERT!$C$7,T1_PERT!$E$7) -> 4.8402248 | I25: =BETAINV(E25,T1_PERT!$F$8,T1_PERT!$G$8,T1_PERT!$C$8,T1_PERT!$E$8) -> 4.5008814 | J25: =BETAINV(RAND(),T1_PERT!$F$9,T1_PERT!$G$9,T1_PERT!$C$9,T1_PERT!$E$9) -> 3.2666851 | K25: =BETAINV(RAND(),T1_PERT!$F$10,T1_PERT!$G$10,T1_PERT!$C$10,T1_PERT!$E$10) -> 2.2351186 | L25: =F25+G25+I25+K25 -> 14.743655 | M25: =F25+H25+J25+K25 -> 14.214989 | N25: =MAX(L25,M25) -> 14.743655
A26: 7 | B26: =NORMSINV(RAND()) -> -1.99867 | C26: =$C$4*B26+SQRT(1-$C$4^2)*NORMSINV(RAND()) -> -1.141315 | D26: =NORMSDIST(B26) -> 0.022822038 | E26: =NORMSDIST(C26) -> 0.12686943 | F26: =BETAINV(RAND(),T1_PERT!$F$5,T1_PERT!$G$5,T1_PERT!$C$5,T1_PERT!$E$5) -> 4.5915192 | G26: =BETAINV(D26,T1_PERT!$F$6,T1_PERT!$G$6,T1_PERT!$C$6,T1_PERT!$E$6) -> 3.456364 | H26: =BETAINV(RAND(),T1_PERT!$F$7,T1_PERT!$G$7,T1_PERT!$C$7,T1_PERT!$E$7) -> 4.9542705 | I26: =BETAINV(E26,T1_PERT!$F$8,T1_PERT!$G$8,T1_PERT!$C$8,T1_PERT!$E$8) -> 4.5145494 | J26: =BETAINV(RAND(),T1_PERT!$F$9,T1_PERT!$G$9,T1_PERT!$C$9,T1_PERT!$E$9) -> 6.3418713 | K26: =BETAINV(RAND(),T1_PERT!$F$10,T1_PERT!$G$10,T1_PERT!$C$10,T1_PERT!$E$10) -> 1.8302203 | L26: =F26+G26+I26+K26 -> 14.392653 | M26: =F26+H26+J26+K26 -> 17.717881 | N26: =MAX(L26,M26) -> 17.717881
A27: 8 | B27: =NORMSINV(RAND()) -> -0.046688332 | C27: =$C$4*B27+SQRT(1-$C$4^2)*NORMSINV(RAND()) -> -1.363431 | D27: =NORMSDIST(B27) -> 0.48138081 | E27: =NORMSDIST(C27) -> 0.08637336 | F27: =BETAINV(RAND(),T1_PERT!$F$5,T1_PERT!$G$5,T1_PERT!$C$5,T1_PERT!$E$5) -> 4.7410361 | G27: =BETAINV(D27,T1_PERT!$F$6,T1_PERT!$G$6,T1_PERT!$C$6,T1_PERT!$E$6) -> 5.1974334 | H27: =BETAINV(RAND(),T1_PERT!$F$7,T1_PERT!$G$7,T1_PERT!$C$7,T1_PERT!$E$7) -> 3.8871449 | I27: =BETAINV(E27,T1_PERT!$F$8,T1_PERT!$G$8,T1_PERT!$C$8,T1_PERT!$E$8) -> 4.413333 | J27: =BETAINV(RAND(),T1_PERT!$F$9,T1_PERT!$G$9,T1_PERT!$C$9,T1_PERT!$E$9) -> 4.0244046 | K27: =BETAINV(RAND(),T1_PERT!$F$10,T1_PERT!$G$10,T1_PERT!$C$10,T1_PERT!$E$10) -> 2.056168 | L27: =F27+G27+I27+K27 -> 16.40797 | M27: =F27+H27+J27+K27 -> 14.708754 | N27: =MAX(L27,M27) -> 16.40797
A28: 9 | B28: =NORMSINV(RAND()) -> -0.28576312 | C28: =$C$4*B28+SQRT(1-$C$4^2)*NORMSINV(RAND()) -> 0.80669156 | D28: =NORMSDIST(B28) -> 0.38752978 | E28: =NORMSDIST(C28) -> 0.7900779 | F28: =BETAINV(RAND(),T1_PERT!$F$5,T1_PERT!$G$5,T1_PERT!$C$5,T1_PERT!$E$5) -> 4.5629086 | G28: =BETAINV(D28,T1_PERT!$F$6,T1_PERT!$G$6,T1_PERT!$C$6,T1_PERT!$E$6) -> 4.9107851 | H28: =BETAINV(RAND(),T1_PERT!$F$7,T1_PERT!$G$7,T1_PERT!$C$7,T1_PERT!$E$7) -> 7.387328 | I28: =BETAINV(E28,T1_PERT!$F$8,T1_PERT!$G$8,T1_PERT!$C$8,T1_PERT!$E$8) -> 5.9306523 | J28: =BETAINV(RAND(),T1_PERT!$F$9,T1_PERT!$G$9,T1_PERT!$C$9,T1_PERT!$E$9) -> 4.3944484 | K28: =BETAINV(RAND(),T1_PERT!$F$10,T1_PERT!$G$10,T1_PERT!$C$10,T1_PERT!$E$10) -> 2.1836225 | L28: =F28+G28+I28+K28 -> 17.587969 | M28: =F28+H28+J28+K28 -> 18.528308 | N28: =MAX(L28,M28) -> 18.528308
A29: 10 | B29: =NORMSINV(RAND()) -> -0.37008815 | C29: =$C$4*B29+SQRT(1-$C$4^2)*NORMSINV(RAND()) -> -2.0527725 | D29: =NORMSDIST(B29) -> 0.3556584 | E29: =NORMSDIST(C29) -> 0.020047321 | F29: =BETAINV(RAND(),T1_PERT!$F$5,T1_PERT!$G$5,T1_PERT!$C$5,T1_PERT!$E$5) -> 4.0716427 | G29: =BETAINV(D29,T1_PERT!$F$6,T1_PERT!$G$6,T1_PERT!$C$6,T1_PERT!$E$6) -> 4.8131774 | H29: =BETAINV(RAND(),T1_PERT!$F$7,T1_PERT!$G$7,T1_PERT!$C$7,T1_PERT!$E$7) -> 5.3494699 | I29: =BETAINV(E29,T1_PERT!$F$8,T1_PERT!$G$8,T1_PERT!$C$8,T1_PERT!$E$8) -> 4.1878107 | J29: =BETAINV(RAND(),T1_PERT!$F$9,T1_PERT!$G$9,T1_PERT!$C$9,T1_PERT!$E$9) -> 4.5240139 | K29: =BETAINV(RAND(),T1_PERT!$F$10,T1_PERT!$G$10,T1_PERT!$C$10,T1_PERT!$E$10) -> 2.1064215 | L29: =F29+G29+I29+K29 -> 15.179052 | M29: =F29+H29+J29+K29 -> 16.051548 | N29: =MAX(L29,M29) -> 16.051548
A30: 11 | B30: =NORMSINV(RAND()) -> -0.9306977 | C30: =$C$4*B30+SQRT(1-$C$4^2)*NORMSINV(RAND()) -> -0.39363652 | D30: =NORMSDIST(B30) -> 0.17600498 | E30: =NORMSDIST(C30) -> 0.34692471 | F30: =BETAINV(RAND(),T1_PERT!$F$5,T1_PERT!$G$5,T1_PERT!$C$5,T1_PERT!$E$5) -> 3.7415438 | G30: =BETAINV(D30,T1_PERT!$F$6,T1_PERT!$G$6,T1_PERT!$C$6,T1_PERT!$E$6) -> 4.2241963 | H30: =BETAINV(RAND(),T1_PERT!$F$7,T1_PERT!$G$7,T1_PERT!$C$7,T1_PERT!$E$7) -> 5.5440916 | I30: =BETAINV(E30,T1_PERT!$F$8,T1_PERT!$G$8,T1_PERT!$C$8,T1_PERT!$E$8) -> 4.961563 | J30: =BETAINV(RAND(),T1_PERT!$F$9,T1_PERT!$G$9,T1_PERT!$C$9,T1_PERT!$E$9) -> 3.4420632 | K30: =BETAINV(RAND(),T1_PERT!$F$10,T1_PERT!$G$10,T1_PERT!$C$10,T1_PERT!$E$10) -> 2.0424941 | L30: =F30+G30+I30+K30 -> 14.969797 | M30: =F30+H30+J30+K30 -> 14.770193 | N30: =MAX(L30,M30) -> 14.969797
A31: 12 | B31: =NORMSINV(RAND()) -> 1.5022649 | C31: =$C$4*B31+SQRT(1-$C$4^2)*NORMSINV(RAND()) -> 1.3466843 | D31: =NORMSDIST(B31) -> 0.93348565 | E31: =NORMSDIST(C31) -> 0.91095903 | F31: =BETAINV(RAND(),T1_PERT!$F$5,T1_PERT!$G$5,T1_PERT!$C$5,T1_PERT!$E$5) -> 4.6689921 | G31: =BETAINV(D31,T1_PERT!$F$6,T1_PERT!$G$6,T1_PERT!$C$6,T1_PERT!$E$6) -> 7.1222639 | H31: =BETAINV(RAND(),T1_PERT!$F$7,T1_PERT!$G$7,T1_PERT!$C$7,T1_PERT!$E$7) -> 5.365147 | I31: =BETAINV(E31,T1_PERT!$F$8,T1_PERT!$G$8,T1_PERT!$C$8,T1_PERT!$E$8) -> 6.3896565 | J31: =BETAINV(RAND(),T1_PERT!$F$9,T1_PERT!$G$9,T1_PERT!$C$9,T1_PERT!$E$9) -> 4.2312136 | K31: =BETAINV(RAND(),T1_PERT!$F$10,T1_PERT!$G$10,T1_PERT!$C$10,T1_PERT!$E$10) -> 1.8884919 | L31: =F31+G31+I31+K31 -> 20.069404 | M31: =F31+H31+J31+K31 -> 16.153845 | N31: =MAX(L31,M31) -> 20.069404
... A5019: 5000 | B5019: =NORMSINV(RAND()) -> -0.054455721 | C5019: =$C$4*B5019+SQRT(1-$C$4^2)*NORMSINV(RAND()) -> 0.13412003 | D5019: =NORMSDIST(B5019) -> 0.47828604 | E5019: =NORMSDIST(C5019) -> 0.55334617 | F5019: =BETAINV(RAND(),T1_PERT!$F$5,T1_PERT!$G$5,T1_PERT!$C$5,T1_PERT!$E$5) -> 3.0474837 | G5019: =BETAINV(D5019,T1_PERT!$F$6,T1_PERT!$G$6,T1_PERT!$C$6,T1_PERT!$E$6) -> 5.1879182 | H5019: =BETAINV(RAND(),T1_PERT!$F$7,T1_PERT!$G$7,T1_PERT!$C$7,T1_PERT!$E$7) -> 6.0208968 | I5019: =BETAINV(E5019,T1_PERT!$F$8,T1_PERT!$G$8,T1_PERT!$C$8,T1_PERT!$E$8) -> 5.362354 | J5019: =BETAINV(RAND(),T1_PERT!$F$9,T1_PERT!$G$9,T1_PERT!$C$9,T1_PERT!$E$9) -> 3.4672337 | K5019: =BETAINV(RAND(),T1_PERT!$F$10,T1_PERT!$G$10,T1_PERT!$C$10,T1_PERT!$E$10) -> 1.6011702 | L5019: =F5019+G5019+I5019+K5019 -> 15.198926 | M5019: =F5019+H5019+J5019+K5019 -> 14.136785 | N5019: =MAX(L5019,M5019) -> 15.198926

Sheet Fin_Inputs
A1: Finance inputs
A2: Must equal data/finance_inputs.json in the tool. Yellow = paste your verified values.
A4: Key | B4: Description | C4: Value | D4: Unit
A5: land_cost_lakh | B5: Land cost, paid at month 0 by equity | C5: 2500 | D5: Rs lakh
A6: approvals_cost_lakh | B6: Approvals, paid at month 0 | C6: 150 | D6: Rs lakh
A7: saleable_area_sqft | B7: Saleable area | C7: 95000 | D7: sq ft
A8: sale_price_per_sqft_inr | B8: Sale price | C8: 9000 | D8: Rs/sq ft
A9: presale_share | B9: Share sold before completion, paid with construction progress | C9: 0.3 | D9: fraction
A10: months_to_sell_after_completion | B10: Months to sell the rest after completion | C10: 12 | D10: months
A11: brokerage_pct | B11: Brokerage, share of collections | C11: 0.02 | D11: fraction
A12: debt_share | B12: Loan share of each month's funding gap | C12: 0.6 | D12: fraction
A13: interest_rate_annual | B13: Loan interest rate | C13: 0.105 | D13: per year
A14: discount_rate_annual | B14: Discount rate for project NPV | C14: 0.12 | D14: per year
A15: equity_discount_rate_annual | B15: Cost of equity, for equity NPV | C15: 0.16 | D15: per year
A16: overhead_per_month_lakh | B16: Site overheads | C16: 12 | D16: Rs lakh/month
... A18: rera_grace_months | B18: Grace months before compensation starts | C18: 0 | D18: months
A20: Scenario settings (for T20 and T21)
A21: cost_multiplier | B21: 1 = plan; 1.10 = flat 10% test (T20) | C21: 1 | D21: x
A22: delay_activity | B22: Activity to delay for the delay test | C22: A28 | D22: id
A23: delay_days | B23: 0 = plan; 60 = delay test (T21) | C23: 0 | D23: days
A25: Derived
A26: im | B26: Monthly loan rate | C26: =(1+Fin_Inputs!$C$13)^(1/12)-1 -> 0.0083551557
A27: rm | B27: Monthly discount rate (project) | C27: =(1+Fin_Inputs!$C$14)^(1/12)-1 -> 0.0094887929
A28: rme | B28: Monthly discount rate (equity) | C28: =(1+Fin_Inputs!$C$15)^(1/12)-1 -> 0.012445138
A29: revenue | B29: Total revenue (Rs lakh) = area x price / 100000 | C29: =Fin_Inputs!$C$7*Fin_Inputs!$C$8/100000 -> 8550

Sheet Fin_Activities
A1: Activities and plan schedule (most-likely durations)
A2: Paste id, name, predecessors, dur_m, cost_m_lakh, daily_cost_lakh from your verified CSV into the yellow columns. Keep activities in order (predecessors above) with no blank rows between them.
A5: id | B5: name | C5: predecessors | D5: dur_m | E5: cost_m_lakh | F5: daily_cost_lakh | G5: Duration used | H5: Cost used (Rs lakh) | I5: ES | J5: EF | K5: Duration (no delay) | L5: ES (no delay) | M5: EF (no delay) | N5: Preds listed | O5: Preds found above | P5: Check
A6: A01 | B6: Mobilisation and site setup | D6: 20 | E6: 40 | F6: 0.05 | G6: =IF(A6="","",D6+IF(A6=Fin_Inputs!$C$22,Fin_Inputs!$C$23,0)) -> 20 | H6: =IF(A6="","",(E6+F6*G6)*Fin_Inputs!$C$21) -> 41 | I6: =IF(A6="","",0) -> 0 | J6: =IF(A6="","",I6+G6) -> 20 | K6: =IF(A6="","",D6) -> 20 | L6: =IF(A6="","",0) -> 0 | M6: =IF(A6="","",L6+K6) -> 20 | N6: =IF(OR(A6="",TRIM(C6)=""),0,LEN(SUBSTITUTE(C6," ",""))-LEN(SUBSTITUTE(SUBSTITUTE(SUBSTITUTE(C6," ",""),",",";"),";",""))+1) -> 0 | O6: 0 | P6: =IF(A6="","",IF(N6=O6,"OK","Predecessor missing or below this row")) -> OK
A7: A02 | B7: Site clearance and survey | C7: A01 | D7: 10 | E7: 10 | F7: 0.02 | G7: =IF(A7="","",D7+IF(A7=Fin_Inputs!$C$22,Fin_Inputs!$C$23,0)) -> 10 | H7: =IF(A7="","",(E7+F7*G7)*Fin_Inputs!$C$21) -> 10.2 | I7: =IF(A7="","",SUMPRODUCT(MAX(ISNUMBER(SEARCH(";"&$A$6:$A$6&";",";"&SUBSTITUTE(SUBSTITUTE($C7," ",""),",",";")&";"))*$J$6:$J$6))) -> 20 | J7: =IF(A7="","",I7+G7) -> 30 | K7: =IF(A7="","",D7) -> 10 | L7: =IF(A7="","",SUMPRODUCT(MAX(ISNUMBER(SEARCH(";"&$A$6:$A$6&";",";"&SUBSTITUTE(SUBSTITUTE($C7," ",""),",",";")&";"))*$M$6:$M$6))) -> 20 | M7: =IF(A7="","",L7+K7) -> 30 | N7: =IF(OR(A7="",TRIM(C7)=""),0,LEN(SUBSTITUTE(C7," ",""))-LEN(SUBSTITUTE(SUBSTITUTE(SUBSTITUTE(C7," ",""),",",";"),";",""))+1) -> 1 | O7: =IF(A7="",0,SUMPRODUCT(--ISNUMBER(SEARCH(";"&$A$6:$A$6&";",";"&SUBSTITUTE(SUBSTITUTE($C7," ",""),",",";")&";")))) -> 1 | P7: =IF(A7="","",IF(N7=O7,"OK","Predecessor missing or below this row")) -> OK
A8: A03 | B8: Piling (bored cast-in-situ) | C8: A02 | D8: 45 | E8: 220 | F8: 0.8 | G8: =IF(A8="","",D8+IF(A8=Fin_Inputs!$C$22,Fin_Inputs!$C$23,0)) -> 45 | H8: =IF(A8="","",(E8+F8*G8)*Fin_Inputs!$C$21) -> 256 | I8: =IF(A8="","",SUMPRODUCT(MAX(ISNUMBER(SEARCH(";"&$A$6:$A$7&";",";"&SUBSTITUTE(SUBSTITUTE($C8," ",""),",",";")&";"))*$J$6:$J$7))) -> 30 | J8: =IF(A8="","",I8+G8) -> 75 | K8: =IF(A8="","",D8) -> 45 | L8: =IF(A8="","",SUMPRODUCT(MAX(ISNUMBER(SEARCH(";"&$A$6:$A$7&";",";"&SUBSTITUTE(SUBSTITUTE($C8," ",""),",",";")&";"))*$M$6:$M$7))) -> 30 | M8: =IF(A8="","",L8+K8) -> 75 | N8: =IF(OR(A8="",TRIM(C8)=""),0,LEN(SUBSTITUTE(C8," ",""))-LEN(SUBSTITUTE(SUBSTITUTE(SUBSTITUTE(C8," ",""),",",";"),";",""))+1) -> 1 | O8: =IF(A8="",0,SUMPRODUCT(--ISNUMBER(SEARCH(";"&$A$6:$A$7&";",";"&SUBSTITUTE(SUBSTITUTE($C8," ",""),",",";")&";")))) -> 1 | P8: =IF(A8="","",IF(N8=O8,"OK","Predecessor missing or below this row")) -> OK
A9: A04 | B9: Excavation for pile caps and raft | C9: A03 | D9: 15 | E9: 45 | F9: 0.3 | G9: =IF(A9="","",D9+IF(A9=Fin_Inputs!$C$22,Fin_Inputs!$C$23,0)) -> 15 | H9: =IF(A9="","",(E9+F9*G9)*Fin_Inputs!$C$21) -> 49.5 | I9: =IF(A9="","",SUMPRODUCT(MAX(ISNUMBER(SEARCH(";"&$A$6:$A$8&";",";"&SUBSTITUTE(SUBSTITUTE($C9," ",""),",",";")&";"))*$J$6:$J$8))) -> 75 | J9: =IF(A9="","",I9+G9) -> 90 | K9: =IF(A9="","",D9) -> 15 | L9: =IF(A9="","",SUMPRODUCT(MAX(ISNUMBER(SEARCH(";"&$A$6:$A$8&";",";"&SUBSTITUTE(SUBSTITUTE($C9," ",""),",",";")&";"))*$M$6:$M$8))) -> 75 | M9: =IF(A9="","",L9+K9) -> 90 | N9: =IF(OR(A9="",TRIM(C9)=""),0,LEN(SUBSTITUTE(C9," ",""))-LEN(SUBSTITUTE(SUBSTITUTE(SUBSTITUTE(C9," ",""),",",";"),";",""))+1) -> 1 | O9: =IF(A9="",0,SUMPRODUCT(--ISNUMBER(SEARCH(";"&$A$6:$A$8&";",";"&SUBSTITUTE(SUBSTITUTE($C9," ",""),",",";")&";")))) -> 1 | P9: =IF(A9="","",IF(N9=O9,"OK","Predecessor missing or below this row")) -> OK
A10: A05 | B10: Pile caps, raft and foundation | C10: A04 | D10: 30 | E10: 180 | F10: 0.1 | G10: =IF(A10="","",D10+IF(A10=Fin_Inputs!$C$22,Fin_Inputs!$C$23,0)) -> 30 | H10: =IF(A10="","",(E10+F10*G10)*Fin_Inputs!$C$21) -> 183 | I10: =IF(A10="","",SUMPRODUCT(MAX(ISNUMBER(SEARCH(";"&$A$6:$A$9&";",";"&SUBSTITUTE(SUBSTITUTE($C10," ",""),",",";")&";"))*$J$6:$J$9))) -> 90 | J10: =IF(A10="","",I10+G10) -> 120 | K10: =IF(A10="","",D10) -> 30 | L10: =IF(A10="","",SUMPRODUCT(MAX(ISNUMBER(SEARCH(";"&$A$6:$A$9&";",";"&SUBSTITUTE(SUBSTITUTE($C10," ",""),",",";")&";"))*$M$6:$M$9))) -> 90 | M10: =IF(A10="","",L10+K10) -> 120 | N10: =IF(OR(A10="",TRIM(C10)=""),0,LEN(SUBSTITUTE(C10," ",""))-LEN(SUBSTITUTE(SUBSTITUTE(SUBSTITUTE(C10," ",""),",",";"),";",""))+1) -> 1 | O10: =IF(A10="",0,SUMPRODUCT(--ISNUMBER(SEARCH(";"&$A$6:$A$9&";",";"&SUBSTITUTE(SUBSTITUTE($C10," ",""),",",";")&";")))) -> 1 | P10: =IF(A10="","",IF(N10=O10,"OK","Predecessor missing or below this row")) -> OK
A11: A06 | B11: Plinth beams and ground floor slab | C11: A05 | D11: 20 | E11: 70 | F11: 0.1 | G11: =IF(A11="","",D11+IF(A11=Fin_Inputs!$C$22,Fin_Inputs!$C$23,0)) -> 20 | H11: =IF(A11="","",(E11+F11*G11)*Fin_Inputs!$C$21) -> 72 | I11: =IF(A11="","",SUMPRODUCT(MAX(ISNUMBER(SEARCH(";"&$A$6:$A$10&";",";"&SUBSTITUTE(SUBSTITUTE($C11," ",""),",",";")&";"))*$J$6:$J$10))) -> 120 | J11: =IF(A11="","",I11+G11) -> 140 | K11: =IF(A11="","",D11) -> 20 | L11: =IF(A11="","",SUMPRODUCT(MAX(ISNUMBER(SEARCH(";"&$A$6:$A$10&";",";"&SUBSTITUTE(SUBSTITUTE($C11," ",""),",",";")&";"))*$M$6:$M$10))) -> 120 | M11: =IF(A11="","",L11+K11) -> 140 | N11: =IF(OR(A11="",TRIM(C11)=""),0,LEN(SUBSTITUTE(C11," ",""))-LEN(SUBSTITUTE(SUBSTITUTE(SUBSTITUTE(C11," ",""),",",";"),";",""))+1) -> 1 | O11: =IF(A11="",0,SUMPRODUCT(--ISNUMBER(SEARCH(";"&$A$6:$A$10&";",";"&SUBSTITUTE(SUBSTITUTE($C11," ",""),",",";")&";")))) -> 1 | P11: =IF(A11="","",IF(N11=O11,"OK","Predecessor missing or below this row")) -> OK
A12: A07 | B12: RCC frame floors 1-5 | C12: A06 | D12: 90 | E12: 380 | F12: 0.6 | G12: =IF(A12="","",D12+IF(A12=Fin_Inputs!$C$22,Fin_Inputs!$C$23,0)) -> 90 | H12: =IF(A12="","",(E12+F12*G12)*Fin_Inputs!$C$21) -> 434 | I12: =IF(A12="","",SUMPRODUCT(MAX(ISNUMBER(SEARCH(";"&$A$6:$A$11&";",";"&SUBSTITUTE(SUBSTITUTE($C12," ",""),",",";")&";"))*$J$6:$J$11))) -> 140 | J12: =IF(A12="","",I12+G12) -> 230 | K12: =IF(A12="","",D12) -> 90 | L12: =IF(A12="","",SUMPRODUCT(MAX(ISNUMBER(SEARCH(";"&$A$6:$A$11&";",";"&SUBSTITUTE(SUBSTITUTE($C12," ",""),",",";")&";"))*$M$6:$M$11))) -> 140 | M12: =IF(A12="","",L12+K12) -> 230 | N12: =IF(OR(A12="",TRIM(C12)=""),0,LEN(SUBSTITUTE(C12," ",""))-LEN(SUBSTITUTE(SUBSTITUTE(SUBSTITUTE(C12," ",""),",",";"),";",""))+1) -> 1 | O12: =IF(A12="",0,SUMPRODUCT(--ISNUMBER(SEARCH(";"&$A$6:$A$11&";",";"&SUBSTITUTE(SUBSTITUTE($C12," ",""),",",";")&";")))) -> 1 | P12: =IF(A12="","",IF(N12=O12,"OK","Predecessor missing or below this row")) -> OK
A13: A08 | B13: RCC frame floors 6-10 and terrace | C13: A07 | D13: 85 | E13: 380 | F13: 0.6 | G13: =IF(A13="","",D13+IF(A13=Fin_Inputs!$C$22,Fin_Inputs!$C$23,0)) -> 85 | H13: =IF(A13="","",(E13+F13*G13)*Fin_Inputs!$C$21) -> 431 | I13: =IF(A13="","",SUMPRODUCT(MAX(ISNUMBER(SEARCH(";"&$A$6:$A$12&";",";"&SUBSTITUTE(SUBSTITUTE($C13," ",""),",",";")&";"))*$J$6:$J$12))) -> 230 | J13: =IF(A13="","",I13+G13) -> 315 | K13: =IF(A13="","",D13) -> 85 | L13: =IF(A13="","",SUMPRODUCT(MAX(ISNUMBER(SEARCH(";"&$A$6:$A$12&";",";"&SUBSTITUTE(SUBSTITUTE($C13," ",""),",",";")&";"))*$M$6:$M$12))) -> 230 | M13: =IF(A13="","",L13+K13) -> 315 | N13: =IF(OR(A13="",TRIM(C13)=""),0,LEN(SUBSTITUTE(C13," ",""))-LEN(SUBSTITUTE(SUBSTITUTE(SUBSTITUTE(C13," ",""),",",";"),";",""))+1) -> 1 | O13: =IF(A13="",0,SUMPRODUCT(--ISNUMBER(SEARCH(";"&$A$6:$A$12&";",";"&SUBSTITUTE(SUBSTITUTE($C13," ",""),",",";")&";")))) -> 1 | P13: =IF(A13="","",IF(N13=O13,"OK","Predecessor missing or below this row")) -> OK
A14: A09 | B14: Masonry floors 1-5 | C14: A07 | D14: 60 | E14: 110 | F14: 0.05 | G14: =IF(A14="","",D14+IF(A14=Fin_Inputs!$C$22,Fin_Inputs!$C$23,0)) -> 60 | H14: =IF(A14="","",(E14+F14*G14)*Fin_Inputs!$C$21) -> 113 | I14: =IF(A14="","",SUMPRODUCT(MAX(ISNUMBER(SEARCH(";"&$A$6:$A$13&";",";"&SUBSTITUTE(SUBSTITUTE($C14," ",""),",",";")&";"))*$J$6:$J$13))) -> 230 | J14: =IF(A14="","",I14+G14) -> 290 | K14: =IF(A14="","",D14) -> 60 | L14: =IF(A14="","",SUMPRODUCT(MAX(ISNUMBER(SEARCH(";"&$A$6:$A$13&";",";"&SUBSTITUTE(SUBSTITUTE($C14," ",""),",",";")&";"))*$M$6:$M$13))) -> 230 | M14: =IF(A14="","",L14+K14) -> 290 | N14: =IF(OR(A14="",TRIM(C14)=""),0,LEN(SUBSTITUTE(C14," ",""))-LEN(SUBSTITUTE(SUBSTITUTE(SUBSTITUTE(C14," ",""),",",";"),";",""))+1) -> 1 | O14: =IF(A14="",0,SUMPRODUCT(--ISNUMBER(SEARCH(";"&$A$6:$A$13&";",";"&SUBSTITUTE(SUBSTITUTE($C14," ",""),",",";")&";")))) -> 1 | P14: =IF(A14="","",IF(N14=O14,"OK","Predecessor missing or below this row")) -> OK
A15: A10 | B15: Masonry floors 6-10 | C15: A08;A09 | D15: 55 | E15: 110 | F15: 0.05 | G15: =IF(A15="","",D15+IF(A15=Fin_Inputs!$C$22,Fin_Inputs!$C$23,0)) -> 55 | H15: =IF(A15="","",(E15+F15*G15)*Fin_Inputs!$C$21) -> 112.75 | I15: =IF(A15="","",SUMPRODUCT(MAX(ISNUMBER(SEARCH(";"&$A$6:$A$14&";",";"&SUBSTITUTE(SUBSTITUTE($C15," ",""),",",";")&";"))*$J$6:$J$14))) -> 315 | J15: =IF(A15="","",I15+G15) -> 370 | K15: =IF(A15="","",D15) -> 55 | L15: =IF(A15="","",SUMPRODUCT(MAX(ISNUMBER(SEARCH(";"&$A$6:$A$14&";",";"&SUBSTITUTE(SUBSTITUTE($C15," ",""),",",";")&";"))*$M$6:$M$14))) -> 315 | M15: =IF(A15="","",L15+K15) -> 370 | N15: =IF(OR(A15="",TRIM(C15)=""),0,LEN(SUBSTITUTE(C15," ",""))-LEN(SUBSTITUTE(SUBSTITUTE(SUBSTITUTE(C15," ",""),",",";"),";",""))+1) -> 2 | O15: =IF(A15="",0,SUMPRODUCT(--ISNUMBER(SEARCH(";"&$A$6:$A$14&";",";"&SUBSTITUTE(SUBSTITUTE($C15," ",""),",",";")&";")))) -> 2 | P15: =IF(A15="","",IF(N15=O15,"OK","Predecessor missing or below this row")) -> OK
A16: A11 | B16: Electrical conduit and plumbing rough-in floors 1-5 | C16: A09 | D16: 45 | E16: 60 | F16: 0.03 | G16: =IF(A16="","",D16+IF(A16=Fin_Inputs!$C$22,Fin_Inputs!$C$23,0)) -> 45 | H16: =IF(A16="","",(E16+F16*G16)*Fin_Inputs!$C$21) -> 61.35 | I16: =IF(A16="","",SUMPRODUCT(MAX(ISNUMBER(SEARCH(";"&$A$6:$A$15&";",";"&SUBSTITUTE(SUBSTITUTE($C16," ",""),",",";")&";"))*$J$6:$J$15))) -> 290 | J16: =IF(A16="","",I16+G16) -> 335 | K16: =IF(A16="","",D16) -> 45 | L16: =IF(A16="","",SUMPRODUCT(MAX(ISNUMBER(SEARCH(";"&$A$6:$A$15&";",";"&SUBSTITUTE(SUBSTITUTE($C16," ",""),",",";")&";"))*$M$6:$M$15))) -> 290 | M16: =IF(A16="","",L16+K16) -> 335 | N16: =IF(OR(A16="",TRIM(C16)=""),0,LEN(SUBSTITUTE(C16," ",""))-LEN(SUBSTITUTE(SUBSTITUTE(SUBSTITUTE(C16," ",""),",",";"),";",""))+1) -> 1 | O16: =IF(A16="",0,SUMPRODUCT(--ISNUMBER(SEARCH(";"&$A$6:$A$15&";",";"&SUBSTITUTE(SUBSTITUTE($C16," ",""),",",";")&";")))) -> 1 | P16: =IF(A16="","",IF(N16=O16,"OK","Predecessor missing or below this row")) -> OK
A17: A12 | B17: Electrical conduit and plumbing rough-in floors 6-10 | C17: A10;A11 | D17: 45 | E17: 60 | F17: 0.03 | G17: =IF(A17="","",D17+IF(A17=Fin_Inputs!$C$22,Fin_Inputs!$C$23,0)) -> 45 | H17: =IF(A17="","",(E17+F17*G17)*Fin_Inputs!$C$21) -> 61.35 | I17: =IF(A17="","",SUMPRODUCT(MAX(ISNUMBER(SEARCH(";"&$A$6:$A$16&";",";"&SUBSTITUTE(SUBSTITUTE($C17," ",""),",",";")&";"))*$J$6:$J$16))) -> 370 | J17: =IF(A17="","",I17+G17) -> 415 | K17: =IF(A17="","",D17) -> 45 | L17: =IF(A17="","",SUMPRODUCT(MAX(ISNUMBER(SEARCH(";"&$A$6:$A$16&";",";"&SUBSTITUTE(SUBSTITUTE($C17," ",""),",",";")&";"))*$M$6:$M$16))) -> 370 | M17: =IF(A17="","",L17+K17) -> 415 | N17: =IF(OR(A17="",TRIM(C17)=""),0,LEN(SUBSTITUTE(C17," ",""))-LEN(SUBSTITUTE(SUBSTITUTE(SUBSTITUTE(C17," ",""),",",";"),";",""))+1) -> 2 | O17: =IF(A17="",0,SUMPRODUCT(--ISNUMBER(SEARCH(";"&$A$6:$A$16&";",";"&SUBSTITUTE(SUBSTITUTE($C17," ",""),",",";")&";")))) -> 2 | P17: =IF(A17="","",IF(N17=O17,"OK","Predecessor missing or below this row")) -> OK
A18: A13 | B18: Internal plastering floors 1-5 | C18: A11 | D18: 45 | E18: 75 | F18: 0.03 | G18: =IF(A18="","",D18+IF(A18=Fin_Inputs!$C$22,Fin_Inputs!$C$23,0)) -> 45 | H18: =IF(A18="","",(E18+F18*G18)*Fin_Inputs!$C$21) -> 76.35 | I18: =IF(A18="","",SUMPRODUCT(MAX(ISNUMBER(SEARCH(";"&$A$6:$A$17&";",";"&SUBSTITUTE(SUBSTITUTE($C18," ",""),",",";")&";"))*$J$6:$J$17))) -> 335 | J18: =IF(A18="","",I18+G18) -> 380 | K18: =IF(A18="","",D18) -> 45 | L18: =IF(A18="","",SUMPRODUCT(MAX(ISNUMBER(SEARCH(";"&$A$6:$A$17&";",";"&SUBSTITUTE(SUBSTITUTE($C18," ",""),",",";")&";"))*$M$6:$M$17))) -> 335 | M18: =IF(A18="","",L18+K18) -> 380 | N18: =IF(OR(A18="",TRIM(C18)=""),0,LEN(SUBSTITUTE(C18," ",""))-LEN(SUBSTITUTE(SUBSTITUTE(SUBSTITUTE(C18," ",""),",",";"),";",""))+1) -> 1 | O18: =IF(A18="",0,SUMPRODUCT(--ISNUMBER(SEARCH(";"&$A$6:$A$17&";",";"&SUBSTITUTE(SUBSTITUTE($C18," ",""),",",";")&";")))) -> 1 | P18: =IF(A18="","",IF(N18=O18,"OK","Predecessor missing or below this row")) -> OK
A19: A14 | B19: Internal plastering floors 6-10 | C19: A12;A13 | D19: 45 | E19: 75 | F19: 0.03 | G19: =IF(A19="","",D19+IF(A19=Fin_Inputs!$C$22,Fin_Inputs!$C$23,0)) -> 45 | H19: =IF(A19="","",(E19+F19*G19)*Fin_Inputs!$C$21) -> 76.35 | I19: =IF(A19="","",SUMPRODUCT(MAX(ISNUMBER(SEARCH(";"&$A$6:$A$18&";",";"&SUBSTITUTE(SUBSTITUTE($C19," ",""),",",";")&";"))*$J$6:$J$18))) -> 415 | J19: =IF(A19="","",I19+G19) -> 460 | K19: =IF(A19="","",D19) -> 45 | L19: =IF(A19="","",SUMPRODUCT(MAX(ISNUMBER(SEARCH(";"&$A$6:$A$18&";",";"&SUBSTITUTE(SUBSTITUTE($C19," ",""),",",";")&";"))*$M$6:$M$18))) -> 415 | M19: =IF(A19="","",L19+K19) -> 460 | N19: =IF(OR(A19="",TRIM(C19)=""),0,LEN(SUBSTITUTE(C19," ",""))-LEN(SUBSTITUTE(SUBSTITUTE(SUBSTITUTE(C19," ",""),",",";"),";",""))+1) -> 2 | O19: =IF(A19="",0,SUMPRODUCT(--ISNUMBER(SEARCH(";"&$A$6:$A$18&";",";"&SUBSTITUTE(SUBSTITUTE($C19," ",""),",",";")&";")))) -> 2 | P19: =IF(A19="","",IF(N19=O19,"OK","Predecessor missing or below this row")) -> OK
A20: A15 | B20: External plaster and facade | C20: A10 | D20: 75 | E20: 140 | F20: 0.15 | G20: =IF(A20="","",D20+IF(A20=Fin_Inputs!$C$22,Fin_Inputs!$C$23,0)) -> 75 | H20: =IF(A20="","",(E20+F20*G20)*Fin_Inputs!$C$21) -> 151.25 | I20: =IF(A20="","",SUMPRODUCT(MAX(ISNUMBER(SEARCH(";"&$A$6:$A$19&";",";"&SUBSTITUTE(SUBSTITUTE($C20," ",""),",",";")&";"))*$J$6:$J$19))) -> 370 | J20: =IF(A20="","",I20+G20) -> 445 | K20: =IF(A20="","",D20) -> 75 | L20: =IF(A20="","",SUMPRODUCT(MAX(ISNUMBER(SEARCH(";"&$A$6:$A$19&";",";"&SUBSTITUTE(SUBSTITUTE($C20," ",""),",",";")&";"))*$M$6:$M$19))) -> 370 | M20: =IF(A20="","",L20+K20) -> 445 | N20: =IF(OR(A20="",TRIM(C20)=""),0,LEN(SUBSTITUTE(C20," ",""))-LEN(SUBSTITUTE(SUBSTITUTE(SUBSTITUTE(C20," ",""),",",";"),";",""))+1) -> 1 | O20: =IF(A20="",0,SUMPRODUCT(--ISNUMBER(SEARCH(";"&$A$6:$A$19&";",";"&SUBSTITUTE(SUBSTITUTE($C20," ",""),",",";")&";")))) -> 1 | P20: =IF(A20="","",IF(N20=O20,"OK","Predecessor missing or below this row")) -> OK
A21: A16 | B21: Waterproofing (terrace and toilets) | C21: A08;A12 | D21: 25 | E21: 45 | F21: 0.02 | G21: =IF(A21="","",D21+IF(A21=Fin_Inputs!$C$22,Fin_Inputs!$C$23,0)) -> 25 | H21: =IF(A21="","",(E21+F21*G21)*Fin_Inputs!$C$21) -> 45.5 | I21: =IF(A21="","",SUMPRODUCT(MAX(ISNUMBER(SEARCH(";"&$A$6:$A$20&";",";"&SUBSTITUTE(SUBSTITUTE($C21," ",""),",",";")&";"))*$J$6:$J$20))) -> 415 | J21: =IF(A21="","",I21+G21) -> 440 | K21: =IF(A21="","",D21) -> 25 | L21: =IF(A21="","",SUMPRODUCT(MAX(ISNUMBER(SEARCH(";"&$A$6:$A$20&";",";"&SUBSTITUTE(SUBSTITUTE($C21," ",""),",",";")&";"))*$M$6:$M$20))) -> 415 | M21: =IF(A21="","",L21+K21) -> 440 | N21: =IF(OR(A21="",TRIM(C21)=""),0,LEN(SUBSTITUTE(C21," ",""))-LEN(SUBSTITUTE(SUBSTITUTE(SUBSTITUTE(C21," ",""),",",";"),";",""))+1) -> 2 | O21: =IF(A21="",0,SUMPRODUCT(--ISNUMBER(SEARCH(";"&$A$6:$A$20&";",";"&SUBSTITUTE(SUBSTITUTE($C21," ",""),",",";")&";")))) -> 2 | P21: =IF(A21="","",IF(N21=O21,"OK","Predecessor missing or below this row")) -> OK
A22: A17 | B22: Flooring and wall tiling | C22: A14;A16 | D22: 75 | E22: 260 | F22: 0.05 | G22: =IF(A22="","",D22+IF(A22=Fin_Inputs!$C$22,Fin_Inputs!$C$23,0)) -> 75 | H22: =IF(A22="","",(E22+F22*G22)*Fin_Inputs!$C$21) -> 263.75 | I22: =IF(A22="","",SUMPRODUCT(MAX(ISNUMBER(SEARCH(";"&$A$6:$A$21&";",";"&SUBSTITUTE(SUBSTITUTE($C22," ",""),",",";")&";"))*$J$6:$J$21))) -> 460 | J22: =IF(A22="","",I22+G22) -> 535 | K22: =IF(A22="","",D22) -> 75 | L22: =IF(A22="","",SUMPRODUCT(MAX(ISNUMBER(SEARCH(";"&$A$6:$A$21&";",";"&SUBSTITUTE(SUBSTITUTE($C22," ",""),",",";")&";"))*$M$6:$M$21))) -> 460 | M22: =IF(A22="","",L22+K22) -> 535 | N22: =IF(OR(A22="",TRIM(C22)=""),0,LEN(SUBSTITUTE(C22," ",""))-LEN(SUBSTITUTE(SUBSTITUTE(SUBSTITUTE(C22," ",""),",",";"),";",""))+1) -> 2 | O22: =IF(A22="",0,SUMPRODUCT(--ISNUMBER(SEARCH(";"&$A$6:$A$21&";",";"&SUBSTITUTE(SUBSTITUTE($C22," ",""),",",";")&";")))) -> 2 | P22: =IF(A22="","",IF(N22=O22,"OK","Predecessor missing or below this row")) -> OK
A23: A18 | B23: Doors, windows and grills | C23: A14 | D23: 50 | E23: 150 | F23: 0.03 | G23: =IF(A23="","",D23+IF(A23=Fin_Inputs!$C$22,Fin_Inputs!$C$23,0)) -> 50 | H23: =IF(A23="","",(E23+F23*G23)*Fin_Inputs!$C$21) -> 151.5 | I23: =IF(A23="","",SUMPRODUCT(MAX(ISNUMBER(SEARCH(";"&$A$6:$A$22&";",";"&SUBSTITUTE(SUBSTITUTE($C23," ",""),",",";")&";"))*$J$6:$J$22))) -> 460 | J23: =IF(A23="","",I23+G23) -> 510 | K23: =IF(A23="","",D23) -> 50 | L23: =IF(A23="","",SUMPRODUCT(MAX(ISNUMBER(SEARCH(";"&$A$6:$A$22&";",";"&SUBSTITUTE(SUBSTITUTE($C23," ",""),",",";")&";"))*$M$6:$M$22))) -> 460 | M23: =IF(A23="","",L23+K23) -> 510 | N23: =IF(OR(A23="",TRIM(C23)=""),0,LEN(SUBSTITUTE(C23," ",""))-LEN(SUBSTITUTE(SUBSTITUTE(SUBSTITUTE(C23," ",""),",",";"),";",""))+1) -> 1 | O23: =IF(A23="",0,SUMPRODUCT(--ISNUMBER(SEARCH(";"&$A$6:$A$22&";",";"&SUBSTITUTE(SUBSTITUTE($C23," ",""),",",";")&";")))) -> 1 | P23: =IF(A23="","",IF(N23=O23,"OK","Predecessor missing or below this row")) -> OK
A24: A19 | B24: Lift supply and installation | C24: A08 | D24: 75 | E24: 120 | F24: 0.03 | G24: =IF(A24="","",D24+IF(A24=Fin_Inputs!$C$22,Fin_Inputs!$C$23,0)) -> 75 | H24: =IF(A24="","",(E24+F24*G24)*Fin_Inputs!$C$21) -> 122.25 | I24: =IF(A24="","",SUMPRODUCT(MAX(ISNUMBER(SEARCH(";"&$A$6:$A$23&";",";"&SUBSTITUTE(SUBSTITUTE($C24," ",""),",",";")&";"))*$J$6:$J$23))) -> 315 | J24: =IF(A24="","",I24+G24) -> 390 | K24: =IF(A24="","",D24) -> 75 | L24: =IF(A24="","",SUMPRODUCT(MAX(ISNUMBER(SEARCH(";"&$A$6:$A$23&";",";"&SUBSTITUTE(SUBSTITUTE($C24," ",""),",",";")&";"))*$M$6:$M$23))) -> 315 | M24: =IF(A24="","",L24+K24) -> 390 | N24: =IF(OR(A24="",TRIM(C24)=""),0,LEN(SUBSTITUTE(C24," ",""))-LEN(SUBSTITUTE(SUBSTITUTE(SUBSTITUTE(C24," ",""),",",";"),";",""))+1) -> 1 | O24: =IF(A24="",0,SUMPRODUCT(--ISNUMBER(SEARCH(";"&$A$6:$A$23&";",";"&SUBSTITUTE(SUBSTITUTE($C24," ",""),",",";")&";")))) -> 1 | P24: =IF(A24="","",IF(N24=O24,"OK","Predecessor missing or below this row")) -> OK
A25: A20 | B25: Electrical wiring and fixtures | C25: A17 | D25: 50 | E25: 140 | F25: 0.03 | G25: =IF(A25="","",D25+IF(A25=Fin_Inputs!$C$22,Fin_Inputs!$C$23,0)) -> 50 | H25: =IF(A25="","",(E25+F25*G25)*Fin_Inputs!$C$21) -> 141.5 | I25: =IF(A25="","",SUMPRODUCT(MAX(ISNUMBER(SEARCH(";"&$A$6:$A$24&";",";"&SUBSTITUTE(SUBSTITUTE($C25," ",""),",",";")&";"))*$J$6:$J$24))) -> 535 | J25: =IF(A25="","",I25+G25) -> 585 | K25: =IF(A25="","",D25) -> 50 | L25: =IF(A25="","",SUMPRODUCT(MAX(ISNUMBER(SEARCH(";"&$A$6:$A$24&";",";"&SUBSTITUTE(SUBSTITUTE($C25," ",""),",",";")&";"))*$M$6:$M$24))) -> 535 | M25: =IF(A25="","",L25+K25) -> 585 | N25: =IF(OR(A25="",TRIM(C25)=""),0,LEN(SUBSTITUTE(C25," ",""))-LEN(SUBSTITUTE(SUBSTITUTE(SUBSTITUTE(C25," ",""),",",";"),";",""))+1) -> 1 | O25: =IF(A25="",0,SUMPRODUCT(--ISNUMBER(SEARCH(";"&$A$6:$A$24&";",";"&SUBSTITUTE(SUBSTITUTE($C25," ",""),",",";")&";")))) -> 1 | P25: =IF(A25="","",IF(N25=O25,"OK","Predecessor missing or below this row")) -> OK
A26: A21 | B26: Plumbing and sanitary fixtures | C26: A17 | D26: 45 | E26: 120 | F26: 0.03 | G26: =IF(A26="","",D26+IF(A26=Fin_Inputs!$C$22,Fin_Inputs!$C$23,0)) -> 45 | H26: =IF(A26="","",(E26+F26*G26)*Fin_Inputs!$C$21) -> 121.35 | I26: =IF(A26="","",SUMPRODUCT(MAX(ISNUMBER(SEARCH(";"&$A$6:$A$25&";",";"&SUBSTITUTE(SUBSTITUTE($C26," ",""),",",";")&";"))*$J$6:$J$25))) -> 535 | J26: =IF(A26="","",I26+G26) -> 580 | K26: =IF(A26="","",D26) -> 45 | L26: =IF(A26="","",SUMPRODUCT(MAX(ISNUMBER(SEARCH(";"&$A$6:$A$25&";",";"&SUBSTITUTE(SUBSTITUTE($C26," ",""),",",";")&";"))*$M$6:$M$25))) -> 535 | M26: =IF(A26="","",L26+K26) -> 580 | N26: =IF(OR(A26="",TRIM(C26)=""),0,LEN(SUBSTITUTE(C26," ",""))-LEN(SUBSTITUTE(SUBSTITUTE(SUBSTITUTE(C26," ",""),",",";"),";",""))+1) -> 1 | O26: =IF(A26="",0,SUMPRODUCT(--ISNUMBER(SEARCH(";"&$A$6:$A$25&";",";"&SUBSTITUTE(SUBSTITUTE($C26," ",""),",",";")&";")))) -> 1 | P26: =IF(A26="","",IF(N26=O26,"OK","Predecessor missing or below this row")) -> OK
A27: A22 | B27: Fire fighting system | C27: A12 | D27: 55 | E27: 90 | F27: 0.03 | G27: =IF(A27="","",D27+IF(A27=Fin_Inputs!$C$22,Fin_Inputs!$C$23,0)) -> 55 | H27: =IF(A27="","",(E27+F27*G27)*Fin_Inputs!$C$21) -> 91.65 | I27: =IF(A27="","",SUMPRODUCT(MAX(ISNUMBER(SEARCH(";"&$A$6:$A$26&";",";"&SUBSTITUTE(SUBSTITUTE($C27," ",""),",",";")&";"))*$J$6:$J$26))) -> 415 | J27: =IF(A27="","",I27+G27) -> 470 | K27: =IF(A27="","",D27) -> 55 | L27: =IF(A27="","",SUMPRODUCT(MAX(ISNUMBER(SEARCH(";"&$A$6:$A$26&";",";"&SUBSTITUTE(SUBSTITUTE($C27," ",""),",",";")&";"))*$M$6:$M$26))) -> 415 | M27: =IF(A27="","",L27+K27) -> 470 | N27: =IF(OR(A27="",TRIM(C27)=""),0,LEN(SUBSTITUTE(C27," ",""))-LEN(SUBSTITUTE(SUBSTITUTE(SUBSTITUTE(C27," ",""),",",";"),";",""))+1) -> 1 | O27: =IF(A27="",0,SUMPRODUCT(--ISNUMBER(SEARCH(";"&$A$6:$A$26&";",";"&SUBSTITUTE(SUBSTITUTE($C27," ",""),",",";")&";")))) -> 1 | P27: =IF(A27="","",IF(N27=O27,"OK","Predecessor missing or below this row")) -> OK
A28: A23 | B28: Internal painting | C28: A18;A20;A21 | D28: 50 | E28: 70 | F28: 0.03 | G28: =IF(A28="","",D28+IF(A28=Fin_Inputs!$C$22,Fin_Inputs!$C$23,0)) -> 50 | H28: =IF(A28="","",(E28+F28*G28)*Fin_Inputs!$C$21) -> 71.5 | I28: =IF(A28="","",SUMPRODUCT(MAX(ISNUMBER(SEARCH(";"&$A$6:$A$27&";",";"&SUBSTITUTE(SUBSTITUTE($C28," ",""),",",";")&";"))*$J$6:$J$27))) -> 585 | J28: =IF(A28="","",I28+G28) -> 635 | K28: =IF(A28="","",D28) -> 50 | L28: =IF(A28="","",SUMPRODUCT(MAX(ISNUMBER(SEARCH(";"&$A$6:$A$27&";",";"&SUBSTITUTE(SUBSTITUTE($C28," ",""),",",";")&";"))*$M$6:$M$27))) -> 585 | M28: =IF(A28="","",L28+K28) -> 635 | N28: =IF(OR(A28="",TRIM(C28)=""),0,LEN(SUBSTITUTE(C28," ",""))-LEN(SUBSTITUTE(SUBSTITUTE(SUBSTITUTE(C28," ",""),",",";"),";",""))+1) -> 3 | O28: =IF(A28="",0,SUMPRODUCT(--ISNUMBER(SEARCH(";"&$A$6:$A$27&";",";"&SUBSTITUTE(SUBSTITUTE($C28," ",""),",",";")&";")))) -> 3 | P28: =IF(A28="","",IF(N28=O28,"OK","Predecessor missing or below this row")) -> OK
A29: A24 | B29: External painting | C29: A15 | D29: 35 | E29: 40 | F29: 0.05 | G29: =IF(A29="","",D29+IF(A29=Fin_Inputs!$C$22,Fin_Inputs!$C$23,0)) -> 35 | H29: =IF(A29="","",(E29+F29*G29)*Fin_Inputs!$C$21) -> 41.75 | I29: =IF(A29="","",SUMPRODUCT(MAX(ISNUMBER(SEARCH(";"&$A$6:$A$28&";",";"&SUBSTITUTE(SUBSTITUTE($C29," ",""),",",";")&";"))*$J$6:$J$28))) -> 445 | J29: =IF(A29="","",I29+G29) -> 480 | K29: =IF(A29="","",D29) -> 35 | L29: =IF(A29="","",SUMPRODUCT(MAX(ISNUMBER(SEARCH(";"&$A$6:$A$28&";",";"&SUBSTITUTE(SUBSTITUTE($C29," ",""),",",";")&";"))*$M$6:$M$28))) -> 445 | M29: =IF(A29="","",L29+K29) -> 480 | N29: =IF(OR(A29="",TRIM(C29)=""),0,LEN(SUBSTITUTE(C29," ",""))-LEN(SUBSTITUTE(SUBSTITUTE(SUBSTITUTE(C29," ",""),",",";"),";",""))+1) -> 1 | O29: =IF(A29="",0,SUMPRODUCT(--ISNUMBER(SEARCH(";"&$A$6:$A$28&";",";"&SUBSTITUTE(SUBSTITUTE($C29," ",""),",",";")&";")))) -> 1 | P29: =IF(A29="","",IF(N29=O29,"OK","Predecessor missing or below this row")) -> OK
A30: A25 | B30: External development (roads, drains, landscaping) | C30: A15 | D30: 60 | E30: 110 | F30: 0.1 | G30: =IF(A30="","",D30+IF(A30=Fin_Inputs!$C$22,Fin_Inputs!$C$23,0)) -> 60 | H30: =IF(A30="","",(E30+F30*G30)*Fin_Inputs!$C$21) -> 116 | I30: =IF(A30="","",SUMPRODUCT(MAX(ISNUMBER(SEARCH(";"&$A$6:$A$29&";",";"&SUBSTITUTE(SUBSTITUTE($C30," ",""),",",";")&";"))*$J$6:$J$29))) -> 445 | J30: =IF(A30="","",I30+G30) -> 505 | K30: =IF(A30="","",D30) -> 60 | L30: =IF(A30="","",SUMPRODUCT(MAX(ISNUMBER(SEARCH(";"&$A$6:$A$29&";",";"&SUBSTITUTE(SUBSTITUTE($C30," ",""),",",";")&";"))*$M$6:$M$29))) -> 445 | M30: =IF(A30="","",L30+K30) -> 505 | N30: =IF(OR(A30="",TRIM(C30)=""),0,LEN(SUBSTITUTE(C30," ",""))-LEN(SUBSTITUTE(SUBSTITUTE(SUBSTITUTE(C30," ",""),",",";"),";",""))+1) -> 1 | O30: =IF(A30="",0,SUMPRODUCT(--ISNUMBER(SEARCH(";"&$A$6:$A$29&";",";"&SUBSTITUTE(SUBSTITUTE($C30," ",""),",",";")&";")))) -> 1 | P30: =IF(A30="","",IF(N30=O30,"OK","Predecessor missing or below this row")) -> OK
A31: A26 | B31: Utilities: substation, STP, water tanks | C31: A08 | D31: 75 | E31: 160 | F31: 0.05 | G31: =IF(A31="","",D31+IF(A31=Fin_Inputs!$C$22,Fin_Inputs!$C$23,0)) -> 75 | H31: =IF(A31="","",(E31+F31*G31)*Fin_Inputs!$C$21) -> 163.75 | I31: =IF(A31="","",SUMPRODUCT(MAX(ISNUMBER(SEARCH(";"&$A$6:$A$30&";",";"&SUBSTITUTE(SUBSTITUTE($C31," ",""),",",";")&";"))*$J$6:$J$30))) -> 315 | J31: =IF(A31="","",I31+G31) -> 390 | K31: =IF(A31="","",D31) -> 75 | L31: =IF(A31="","",SUMPRODUCT(MAX(ISNUMBER(SEARCH(";"&$A$6:$A$30&";",";"&SUBSTITUTE(SUBSTITUTE($C31," ",""),",",";")&";"))*$M$6:$M$30))) -> 315 | M31: =IF(A31="","",L31+K31) -> 390 | N31: =IF(OR(A31="",TRIM(C31)=""),0,LEN(SUBSTITUTE(C31," ",""))-LEN(SUBSTITUTE(SUBSTITUTE(SUBSTITUTE(C31," ",""),",",";"),";",""))+1) -> 1 | O31: =IF(A31="",0,SUMPRODUCT(--ISNUMBER(SEARCH(";"&$A$6:$A$30&";",";"&SUBSTITUTE(SUBSTITUTE($C31," ",""),",",";")&";")))) -> 1 | P31: =IF(A31="","",IF(N31=O31,"OK","Predecessor missing or below this row")) -> OK
A32: A27 | B32: Testing and commissioning | C32: A19;A22;A23;A26 | D32: 20 | E32: 15 | F32: 0.05 | G32: =IF(A32="","",D32+IF(A32=Fin_Inputs!$C$22,Fin_Inputs!$C$23,0)) -> 20 | H32: =IF(A32="","",(E32+F32*G32)*Fin_Inputs!$C$21) -> 16 | I32: =IF(A32="","",SUMPRODUCT(MAX(ISNUMBER(SEARCH(";"&$A$6:$A$31&";",";"&SUBSTITUTE(SUBSTITUTE($C32," ",""),",",";")&";"))*$J$6:$J$31))) -> 635 | J32: =IF(A32="","",I32+G32) -> 655 | K32: =IF(A32="","",D32) -> 20 | L32: =IF(A32="","",SUMPRODUCT(MAX(ISNUMBER(SEARCH(";"&$A$6:$A$31&";",";"&SUBSTITUTE(SUBSTITUTE($C32," ",""),",",";")&";"))*$M$6:$M$31))) -> 635 | M32: =IF(A32="","",L32+K32) -> 655 | N32: =IF(OR(A32="",TRIM(C32)=""),0,LEN(SUBSTITUTE(C32," ",""))-LEN(SUBSTITUTE(SUBSTITUTE(SUBSTITUTE(C32," ",""),",",";"),";",""))+1) -> 4 | O32: =IF(A32="",0,SUMPRODUCT(--ISNUMBER(SEARCH(";"&$A$6:$A$31&";",";"&SUBSTITUTE(SUBSTITUTE($C32," ",""),",",";")&";")))) -> 4 | P32: =IF(A32="","",IF(N32=O32,"OK","Predecessor missing or below this row")) -> OK
A33: A28 | B33: Occupancy certificate and handover | C33: A24;A25;A27 | D33: 45 | E33: 20 | F33: 0.05 | G33: =IF(A33="","",D33+IF(A33=Fin_Inputs!$C$22,Fin_Inputs!$C$23,0)) -> 45 | H33: =IF(A33="","",(E33+F33*G33)*Fin_Inputs!$C$21) -> 22.25 | I33: =IF(A33="","",SUMPRODUCT(MAX(ISNUMBER(SEARCH(";"&$A$6:$A$32&";",";"&SUBSTITUTE(SUBSTITUTE($C33," ",""),",",";")&";"))*$J$6:$J$32))) -> 655 | J33: =IF(A33="","",I33+G33) -> 700 | K33: =IF(A33="","",D33) -> 45 | L33: =IF(A33="","",SUMPRODUCT(MAX(ISNUMBER(SEARCH(";"&$A$6:$A$32&";",";"&SUBSTITUTE(SUBSTITUTE($C33," ",""),",",";")&";"))*$M$6:$M$32))) -> 655 | M33: =IF(A33="","",L33+K33) -> 700 | N33: =IF(OR(A33="",TRIM(C33)=""),0,LEN(SUBSTITUTE(C33," ",""))-LEN(SUBSTITUTE(SUBSTITUTE(SUBSTITUTE(C33," ",""),",",";"),";",""))+1) -> 3 | O33: =IF(A33="",0,SUMPRODUCT(--ISNUMBER(SEARCH(";"&$A$6:$A$32&";",";"&SUBSTITUTE(SUBSTITUTE($C33," ",""),",",";")&";")))) -> 3 | P33: =IF(A33="","",IF(N33=O33,"OK","Predecessor missing or below this row")) -> OK
G34: =IF(A34="","",D34+IF(A34=Fin_Inputs!$C$22,Fin_Inputs!$C$23,0)) | H34: =IF(A34="","",(E34+F34*G34)*Fin_Inputs!$C$21) | I34: =IF(A34="","",SUMPRODUCT(MAX(ISNUMBER(SEARCH(";"&$A$6:$A$33&";",";"&SUBSTITUTE(SUBSTITUTE($C34," ",""),",",";")&";"))*$J$6:$J$33))) | J34: =IF(A34="","",I34+G34) | K34: =IF(A34="","",D34) | L34: =IF(A34="","",SUMPRODUCT(MAX(ISNUMBER(SEARCH(";"&$A$6:$A$33&";",";"&SUBSTITUTE(SUBSTITUTE($C34," ",""),",",";")&";"))*$M$6:$M$33))) | M34: =IF(A34="","",L34+K34) | N34: =IF(OR(A34="",TRIM(C34)=""),0,LEN(SUBSTITUTE(C34," ",""))-LEN(SUBSTITUTE(SUBSTITUTE(SUBSTITUTE(C34," ",""),",",";"),";",""))+1) -> 0 | O34: =IF(A34="",0,SUMPRODUCT(--ISNUMBER(SEARCH(";"&$A$6:$A$33&";",";"&SUBSTITUTE(SUBSTITUTE($C34," ",""),",",";")&";")))) -> 0 | P34: =IF(A34="","",IF(N34=O34,"OK","Predecessor missing or below this row"))
G35: =IF(A35="","",D35+IF(A35=Fin_Inputs!$C$22,Fin_Inputs!$C$23,0)) | H35: =IF(A35="","",(E35+F35*G35)*Fin_Inputs!$C$21) | I35: =IF(A35="","",SUMPRODUCT(MAX(ISNUMBER(SEARCH(";"&$A$6:$A$34&";",";"&SUBSTITUTE(SUBSTITUTE($C35," ",""),",",";")&";"))*$J$6:$J$34))) | J35: =IF(A35="","",I35+G35) | K35: =IF(A35="","",D35) | L35: =IF(A35="","",SUMPRODUCT(MAX(ISNUMBER(SEARCH(";"&$A$6:$A$34&";",";"&SUBSTITUTE(SUBSTITUTE($C35," ",""),",",";")&";"))*$M$6:$M$34))) | M35: =IF(A35="","",L35+K35) | N35: =IF(OR(A35="",TRIM(C35)=""),0,LEN(SUBSTITUTE(C35," ",""))-LEN(SUBSTITUTE(SUBSTITUTE(SUBSTITUTE(C35," ",""),",",";"),";",""))+1) -> 0 | O35: =IF(A35="",0,SUMPRODUCT(--ISNUMBER(SEARCH(";"&$A$6:$A$34&";",";"&SUBSTITUTE(SUBSTITUTE($C35," ",""),",",";")&";")))) -> 0 | P35: =IF(A35="","",IF(N35=O35,"OK","Predecessor missing or below this row"))
G36: =IF(A36="","",D36+IF(A36=Fin_Inputs!$C$22,Fin_Inputs!$C$23,0)) | H36: =IF(A36="","",(E36+F36*G36)*Fin_Inputs!$C$21) | I36: =IF(A36="","",SUMPRODUCT(MAX(ISNUMBER(SEARCH(";"&$A$6:$A$35&";",";"&SUBSTITUTE(SUBSTITUTE($C36," ",""),",",";")&";"))*$J$6:$J$35))) | J36: =IF(A36="","",I36+G36) | K36: =IF(A36="","",D36) | L36: =IF(A36="","",SUMPRODUCT(MAX(ISNUMBER(SEARCH(";"&$A$6:$A$35&";",";"&SUBSTITUTE(SUBSTITUTE($C36," ",""),",",";")&";"))*$M$6:$M$35))) | M36: =IF(A36="","",L36+K36) | N36: =IF(OR(A36="",TRIM(C36)=""),0,LEN(SUBSTITUTE(C36," ",""))-LEN(SUBSTITUTE(SUBSTITUTE(SUBSTITUTE(C36," ",""),",",";"),";",""))+1) -> 0 | O36: =IF(A36="",0,SUMPRODUCT(--ISNUMBER(SEARCH(";"&$A$6:$A$35&";",";"&SUBSTITUTE(SUBSTITUTE($C36," ",""),",",";")&";")))) -> 0 | P36: =IF(A36="","",IF(N36=O36,"OK","Predecessor missing or below this row"))
G37: =IF(A37="","",D37+IF(A37=Fin_Inputs!$C$22,Fin_Inputs!$C$23,0)) | H37: =IF(A37="","",(E37+F37*G37)*Fin_Inputs!$C$21) | I37: =IF(A37="","",SUMPRODUCT(MAX(ISNUMBER(SEARCH(";"&$A$6:$A$36&";",";"&SUBSTITUTE(SUBSTITUTE($C37," ",""),",",";")&";"))*$J$6:$J$36))) | J37: =IF(A37="","",I37+G37) | K37: =IF(A37="","",D37) | L37: =IF(A37="","",SUMPRODUCT(MAX(ISNUMBER(SEARCH(";"&$A$6:$A$36&";",";"&SUBSTITUTE(SUBSTITUTE($C37," ",""),",",";")&";"))*$M$6:$M$36))) | M37: =IF(A37="","",L37+K37) | N37: =IF(OR(A37="",TRIM(C37)=""),0,LEN(SUBSTITUTE(C37," ",""))-LEN(SUBSTITUTE(SUBSTITUTE(SUBSTITUTE(C37," ",""),",",";"),";",""))+1) -> 0 | O37: =IF(A37="",0,SUMPRODUCT(--ISNUMBER(SEARCH(";"&$A$6:$A$36&";",";"&SUBSTITUTE(SUBSTITUTE($C37," ",""),",",";")&";")))) -> 0 | P37: =IF(A37="","",IF(N37=O37,"OK","Predecessor missing or below this row"))
G38: =IF(A38="","",D38+IF(A38=Fin_Inputs!$C$22,Fin_Inputs!$C$23,0)) | H38: =IF(A38="","",(E38+F38*G38)*Fin_Inputs!$C$21) | I38: =IF(A38="","",SUMPRODUCT(MAX(ISNUMBER(SEARCH(";"&$A$6:$A$37&";",";"&SUBSTITUTE(SUBSTITUTE($C38," ",""),",",";")&";"))*$J$6:$J$37))) | J38: =IF(A38="","",I38+G38) | K38: =IF(A38="","",D38) | L38: =IF(A38="","",SUMPRODUCT(MAX(ISNUMBER(SEARCH(";"&$A$6:$A$37&";",";"&SUBSTITUTE(SUBSTITUTE($C38," ",""),",",";")&";"))*$M$6:$M$37))) | M38: =IF(A38="","",L38+K38) | N38: =IF(OR(A38="",TRIM(C38)=""),0,LEN(SUBSTITUTE(C38," ",""))-LEN(SUBSTITUTE(SUBSTITUTE(SUBSTITUTE(C38," ",""),",",";"),";",""))+1) -> 0 | O38: =IF(A38="",0,SUMPRODUCT(--ISNUMBER(SEARCH(";"&$A$6:$A$37&";",";"&SUBSTITUTE(SUBSTITUTE($C38," ",""),",",";")&";")))) -> 0 | P38: =IF(A38="","",IF(N38=O38,"OK","Predecessor missing or below this row"))
G39: =IF(A39="","",D39+IF(A39=Fin_Inputs!$C$22,Fin_Inputs!$C$23,0)) | H39: =IF(A39="","",(E39+F39*G39)*Fin_Inputs!$C$21) | I39: =IF(A39="","",SUMPRODUCT(MAX(ISNUMBER(SEARCH(";"&$A$6:$A$38&";",";"&SUBSTITUTE(SUBSTITUTE($C39," ",""),",",";")&";"))*$J$6:$J$38))) | J39: =IF(A39="","",I39+G39) | K39: =IF(A39="","",D39) | L39: =IF(A39="","",SUMPRODUCT(MAX(ISNUMBER(SEARCH(";"&$A$6:$A$38&";",";"&SUBSTITUTE(SUBSTITUTE($C39," ",""),",",";")&";"))*$M$6:$M$38))) | M39: =IF(A39="","",L39+K39) | N39: =IF(OR(A39="",TRIM(C39)=""),0,LEN(SUBSTITUTE(C39," ",""))-LEN(SUBSTITUTE(SUBSTITUTE(SUBSTITUTE(C39," ",""),",",";"),";",""))+1) -> 0 | O39: =IF(A39="",0,SUMPRODUCT(--ISNUMBER(SEARCH(";"&$A$6:$A$38&";",";"&SUBSTITUTE(SUBSTITUTE($C39," ",""),",",";")&";")))) -> 0 | P39: =IF(A39="","",IF(N39=O39,"OK","Predecessor missing or below this row"))
G40: =IF(A40="","",D40+IF(A40=Fin_Inputs!$C$22,Fin_Inputs!$C$23,0)) | H40: =IF(A40="","",(E40+F40*G40)*Fin_Inputs!$C$21) | I40: =IF(A40="","",SUMPRODUCT(MAX(ISNUMBER(SEARCH(";"&$A$6:$A$39&";",";"&SUBSTITUTE(SUBSTITUTE($C40," ",""),",",";")&";"))*$J$6:$J$39))) | J40: =IF(A40="","",I40+G40) | K40: =IF(A40="","",D40) | L40: =IF(A40="","",SUMPRODUCT(MAX(ISNUMBER(SEARCH(";"&$A$6:$A$39&";",";"&SUBSTITUTE(SUBSTITUTE($C40," ",""),",",";")&";"))*$M$6:$M$39))) | M40: =IF(A40="","",L40+K40) | N40: =IF(OR(A40="",TRIM(C40)=""),0,LEN(SUBSTITUTE(C40," ",""))-LEN(SUBSTITUTE(SUBSTITUTE(SUBSTITUTE(C40," ",""),",",";"),";",""))+1) -> 0 | O40: =IF(A40="",0,SUMPRODUCT(--ISNUMBER(SEARCH(";"&$A$6:$A$39&";",";"&SUBSTITUTE(SUBSTITUTE($C40," ",""),",",";")&";")))) -> 0 | P40: =IF(A40="","",IF(N40=O40,"OK","Predecessor missing or below this row"))
G41: =IF(A41="","",D41+IF(A41=Fin_Inputs!$C$22,Fin_Inputs!$C$23,0)) | H41: =IF(A41="","",(E41+F41*G41)*Fin_Inputs!$C$21) | I41: =IF(A41="","",SUMPRODUCT(MAX(ISNUMBER(SEARCH(";"&$A$6:$A$40&";",";"&SUBSTITUTE(SUBSTITUTE($C41," ",""),",",";")&";"))*$J$6:$J$40))) | J41: =IF(A41="","",I41+G41) | K41: =IF(A41="","",D41) | L41: =IF(A41="","",SUMPRODUCT(MAX(ISNUMBER(SEARCH(";"&$A$6:$A$40&";",";"&SUBSTITUTE(SUBSTITUTE($C41," ",""),",",";")&";"))*$M$6:$M$40))) | M41: =IF(A41="","",L41+K41) | N41: =IF(OR(A41="",TRIM(C41)=""),0,LEN(SUBSTITUTE(C41," ",""))-LEN(SUBSTITUTE(SUBSTITUTE(SUBSTITUTE(C41," ",""),",",";"),";",""))+1) -> 0 | O41: =IF(A41="",0,SUMPRODUCT(--ISNUMBER(SEARCH(";"&$A$6:$A$40&";",";"&SUBSTITUTE(SUBSTITUTE($C41," ",""),",",";")&";")))) -> 0 | P41: =IF(A41="","",IF(N41=O41,"OK","Predecessor missing or below this row"))
G42: =IF(A42="","",D42+IF(A42=Fin_Inputs!$C$22,Fin_Inputs!$C$23,0)) | H42: =IF(A42="","",(E42+F42*G42)*Fin_Inputs!$C$21) | I42: =IF(A42="","",SUMPRODUCT(MAX(ISNUMBER(SEARCH(";"&$A$6:$A$41&";",";"&SUBSTITUTE(SUBSTITUTE($C42," ",""),",",";")&";"))*$J$6:$J$41))) | J42: =IF(A42="","",I42+G42) | K42: =IF(A42="","",D42) | L42: =IF(A42="","",SUMPRODUCT(MAX(ISNUMBER(SEARCH(";"&$A$6:$A$41&";",";"&SUBSTITUTE(SUBSTITUTE($C42," ",""),",",";")&";"))*$M$6:$M$41))) | M42: =IF(A42="","",L42+K42) | N42: =IF(OR(A42="",TRIM(C42)=""),0,LEN(SUBSTITUTE(C42," ",""))-LEN(SUBSTITUTE(SUBSTITUTE(SUBSTITUTE(C42," ",""),",",";"),";",""))+1) -> 0 | O42: =IF(A42="",0,SUMPRODUCT(--ISNUMBER(SEARCH(";"&$A$6:$A$41&";",";"&SUBSTITUTE(SUBSTITUTE($C42," ",""),",",";")&";")))) -> 0 | P42: =IF(A42="","",IF(N42=O42,"OK","Predecessor missing or below this row"))
G43: =IF(A43="","",D43+IF(A43=Fin_Inputs!$C$22,Fin_Inputs!$C$23,0)) | H43: =IF(A43="","",(E43+F43*G43)*Fin_Inputs!$C$21) | I43: =IF(A43="","",SUMPRODUCT(MAX(ISNUMBER(SEARCH(";"&$A$6:$A$42&";",";"&SUBSTITUTE(SUBSTITUTE($C43," ",""),",",";")&";"))*$J$6:$J$42))) | J43: =IF(A43="","",I43+G43) | K43: =IF(A43="","",D43) | L43: =IF(A43="","",SUMPRODUCT(MAX(ISNUMBER(SEARCH(";"&$A$6:$A$42&";",";"&SUBSTITUTE(SUBSTITUTE($C43," ",""),",",";")&";"))*$M$6:$M$42))) | M43: =IF(A43="","",L43+K43) | N43: =IF(OR(A43="",TRIM(C43)=""),0,LEN(SUBSTITUTE(C43," ",""))-LEN(SUBSTITUTE(SUBSTITUTE(SUBSTITUTE(C43," ",""),",",";"),";",""))+1) -> 0 | O43: =IF(A43="",0,SUMPRODUCT(--ISNUMBER(SEARCH(";"&$A$6:$A$42&";",";"&SUBSTITUTE(SUBSTITUTE($C43," ",""),",",";")&";")))) -> 0 | P43: =IF(A43="","",IF(N43=O43,"OK","Predecessor missing or below this row"))
G44: =IF(A44="","",D44+IF(A44=Fin_Inputs!$C$22,Fin_Inputs!$C$23,0)) | H44: =IF(A44="","",(E44+F44*G44)*Fin_Inputs!$C$21) | I44: =IF(A44="","",SUMPRODUCT(MAX(ISNUMBER(SEARCH(";"&$A$6:$A$43&";",";"&SUBSTITUTE(SUBSTITUTE($C44," ",""),",",";")&";"))*$J$6:$J$43))) | J44: =IF(A44="","",I44+G44) | K44: =IF(A44="","",D44) | L44: =IF(A44="","",SUMPRODUCT(MAX(ISNUMBER(SEARCH(";"&$A$6:$A$43&";",";"&SUBSTITUTE(SUBSTITUTE($C44," ",""),",",";")&";"))*$M$6:$M$43))) | M44: =IF(A44="","",L44+K44) | N44: =IF(OR(A44="",TRIM(C44)=""),0,LEN(SUBSTITUTE(C44," ",""))-LEN(SUBSTITUTE(SUBSTITUTE(SUBSTITUTE(C44," ",""),",",";"),";",""))+1) -> 0 | O44: =IF(A44="",0,SUMPRODUCT(--ISNUMBER(SEARCH(";"&$A$6:$A$43&";",";"&SUBSTITUTE(SUBSTITUTE($C44," ",""),",",";")&";")))) -> 0 | P44: =IF(A44="","",IF(N44=O44,"OK","Predecessor missing or below this row"))
G45: =IF(A45="","",D45+IF(A45=Fin_Inputs!$C$22,Fin_Inputs!$C$23,0)) | H45: =IF(A45="","",(E45+F45*G45)*Fin_Inputs!$C$21) | I45: =IF(A45="","",SUMPRODUCT(MAX(ISNUMBER(SEARCH(";"&$A$6:$A$44&";",";"&SUBSTITUTE(SUBSTITUTE($C45," ",""),",",";")&";"))*$J$6:$J$44))) | J45: =IF(A45="","",I45+G45) | K45: =IF(A45="","",D45) | L45: =IF(A45="","",SUMPRODUCT(MAX(ISNUMBER(SEARCH(";"&$A$6:$A$44&";",";"&SUBSTITUTE(SUBSTITUTE($C45," ",""),",",";")&";"))*$M$6:$M$44))) | M45: =IF(A45="","",L45+K45) | N45: =IF(OR(A45="",TRIM(C45)=""),0,LEN(SUBSTITUTE(C45," ",""))-LEN(SUBSTITUTE(SUBSTITUTE(SUBSTITUTE(C45," ",""),",",";"),";",""))+1) -> 0 | O45: =IF(A45="",0,SUMPRODUCT(--ISNUMBER(SEARCH(";"&$A$6:$A$44&";",";"&SUBSTITUTE(SUBSTITUTE($C45," ",""),",",";")&";")))) -> 0 | P45: =IF(A45="","",IF(N45=O45,"OK","Predecessor missing or below this row"))
B47: Project duration (days) | C47: =MAX(J6:J45) -> 700
B48: Plan duration without delay (days) | C48: =MAX(M6:M45) -> 700
B49: Completion month | C49: =CEILING(MAX(J6:J45)/30,1) -> 24
B50: Promised month (plan + grace) | C50: =CEILING(MAX(M6:M45)/30,1)+Fin_Inputs!$C$18 -> 24
B51: Total activity cost (Rs lakh) | C51: =SUM(H6:H45) -> 3497.85
B52: Rows with problems | C52: =COUNTIF(P6:P45,"Predecessor*") -> 0

Sheet Fin_Spread
A1: Construction spend by month
A2: Each activity's cost spread evenly over its days: overlap of the activity with the month / duration x cost.
A5: id | B5: ES | C5: Duration | D5: EF | E5: Cost | F5: 1 | G5: 2 | H5: 3 | I5: 4 | J5: 5 | K5: 6 | L5: 7 | M5: 8 | N5: 9 | O5: 10 | P5: 11 | Q5: 12 | R5: 13 | S5: 14 | T5: 15 | U5: 16 | V5: 17 | W5: 18 | X5: 19 | Y5: 20 | Z5: 21 | AA5: 22 | AB5: 23 | AC5: 24 | AD5: 25 | AE5: 26 | AF5: 27 | AG5: 28 | AH5: 29 | AI5: 30 | AJ5: 31 | AK5: 32 | AL5: 33 | AM5: 34 | AN5: 35 | AO5: 36 | AP5: 37 | AQ5: 38 | AR5: 39 | AS5: 40 | AT5: 41 | AU5: 42 | AV5: 43 | AW5: 44 | AX5: 45 | AY5: 46 | AZ5: 47 | BA5: 48 | BB5: 49 | BC5: 50 | BD5: 51 | BE5: 52 | BF5: 53 | BG5: 54 | BH5: 55 | BI5: 56 | BJ5: 57 | BK5: 58 | BL5: 59 | BM5: 60
A6: =IF(Fin_Activities!$A6="","",Fin_Activities!A6) -> A01 | B6: =IF(Fin_Activities!$A6="","",Fin_Activities!I6) -> 0 | C6: =IF(Fin_Activities!$A6="","",Fin_Activities!G6) -> 20 | D6: =IF(Fin_Activities!$A6="","",Fin_Activities!J6) -> 20 | E6: =IF(Fin_Activities!$A6="","",Fin_Activities!H6) -> 41 | F6: =IF(OR($A6="",$E6=0),0,IF($C6<=0,IF(AND($B6>=(F$5-1)*30,$B6<F$5*30),$E6,0),MAX(0,MIN($D6,F$5*30)-MAX($B6,(F$5-1)*30))/$C6*$E6)) -> 41 | G6: =IF(OR($A6="",$E6=0),0,IF($C6<=0,IF(AND($B6>=(G$5-1)*30,$B6<G$5*30),$E6,0),MAX(0,MIN($D6,G$5*30)-MAX($B6,(G$5-1)*30))/$C6*$E6)) -> 0 | H6: =IF(OR($A6="",$E6=0),0,IF($C6<=0,IF(AND($B6>=(H$5-1)*30,$B6<H$5*30),$E6,0),MAX(0,MIN($D6,H$5*30)-MAX($B6,(H$5-1)*30))/$C6*$E6)) -> 0 | I6: =IF(OR($A6="",$E6=0),0,IF($C6<=0,IF(AND($B6>=(I$5-1)*30,$B6<I$5*30),$E6,0),MAX(0,MIN($D6,I$5*30)-MAX($B6,(I$5-1)*30))/$C6*$E6)) -> 0 | J6: =IF(OR($A6="",$E6=0),0,IF($C6<=0,IF(AND($B6>=(J$5-1)*30,$B6<J$5*30),$E6,0),MAX(0,MIN($D6,J$5*30)-MAX($B6,(J$5-1)*30))/$C6*$E6)) -> 0 | K6: =IF(OR($A6="",$E6=0),0,IF($C6<=0,IF(AND($B6>=(K$5-1)*30,$B6<K$5*30),$E6,0),MAX(0,MIN($D6,K$5*30)-MAX($B6,(K$5-1)*30))/$C6*$E6)) -> 0 | L6: =IF(OR($A6="",$E6=0),0,IF($C6<=0,IF(AND($B6>=(L$5-1)*30,$B6<L$5*30),$E6,0),MAX(0,MIN($D6,L$5*30)-MAX($B6,(L$5-1)*30))/$C6*$E6)) -> 0 | M6: =IF(OR($A6="",$E6=0),0,IF($C6<=0,IF(AND($B6>=(M$5-1)*30,$B6<M$5*30),$E6,0),MAX(0,MIN($D6,M$5*30)-MAX($B6,(M$5-1)*30))/$C6*$E6)) -> 0 | ... BM6: =IF(OR($A6="",$E6=0),0,IF($C6<=0,IF(AND($B6>=(BM$5-1)*30,$B6<BM$5*30),$E6,0),MAX(0,MIN($D6,BM$5*30)-MAX($B6,(BM$5-1)*30))/$C6*$E6)) -> 0
A7: =IF(Fin_Activities!$A7="","",Fin_Activities!A7) -> A02 | B7: =IF(Fin_Activities!$A7="","",Fin_Activities!I7) -> 20 | C7: =IF(Fin_Activities!$A7="","",Fin_Activities!G7) -> 10 | D7: =IF(Fin_Activities!$A7="","",Fin_Activities!J7) -> 30 | E7: =IF(Fin_Activities!$A7="","",Fin_Activities!H7) -> 10.2 | F7: =IF(OR($A7="",$E7=0),0,IF($C7<=0,IF(AND($B7>=(F$5-1)*30,$B7<F$5*30),$E7,0),MAX(0,MIN($D7,F$5*30)-MAX($B7,(F$5-1)*30))/$C7*$E7)) -> 10.2 | G7: =IF(OR($A7="",$E7=0),0,IF($C7<=0,IF(AND($B7>=(G$5-1)*30,$B7<G$5*30),$E7,0),MAX(0,MIN($D7,G$5*30)-MAX($B7,(G$5-1)*30))/$C7*$E7)) -> 0 | H7: =IF(OR($A7="",$E7=0),0,IF($C7<=0,IF(AND($B7>=(H$5-1)*30,$B7<H$5*30),$E7,0),MAX(0,MIN($D7,H$5*30)-MAX($B7,(H$5-1)*30))/$C7*$E7)) -> 0 | I7: =IF(OR($A7="",$E7=0),0,IF($C7<=0,IF(AND($B7>=(I$5-1)*30,$B7<I$5*30),$E7,0),MAX(0,MIN($D7,I$5*30)-MAX($B7,(I$5-1)*30))/$C7*$E7)) -> 0 | J7: =IF(OR($A7="",$E7=0),0,IF($C7<=0,IF(AND($B7>=(J$5-1)*30,$B7<J$5*30),$E7,0),MAX(0,MIN($D7,J$5*30)-MAX($B7,(J$5-1)*30))/$C7*$E7)) -> 0 | K7: =IF(OR($A7="",$E7=0),0,IF($C7<=0,IF(AND($B7>=(K$5-1)*30,$B7<K$5*30),$E7,0),MAX(0,MIN($D7,K$5*30)-MAX($B7,(K$5-1)*30))/$C7*$E7)) -> 0 | L7: =IF(OR($A7="",$E7=0),0,IF($C7<=0,IF(AND($B7>=(L$5-1)*30,$B7<L$5*30),$E7,0),MAX(0,MIN($D7,L$5*30)-MAX($B7,(L$5-1)*30))/$C7*$E7)) -> 0 | M7: =IF(OR($A7="",$E7=0),0,IF($C7<=0,IF(AND($B7>=(M$5-1)*30,$B7<M$5*30),$E7,0),MAX(0,MIN($D7,M$5*30)-MAX($B7,(M$5-1)*30))/$C7*$E7)) -> 0 | ... BM7: =IF(OR($A7="",$E7=0),0,IF($C7<=0,IF(AND($B7>=(BM$5-1)*30,$B7<BM$5*30),$E7,0),MAX(0,MIN($D7,BM$5*30)-MAX($B7,(BM$5-1)*30))/$C7*$E7)) -> 0
A8: =IF(Fin_Activities!$A8="","",Fin_Activities!A8) -> A03 | B8: =IF(Fin_Activities!$A8="","",Fin_Activities!I8) -> 30 | C8: =IF(Fin_Activities!$A8="","",Fin_Activities!G8) -> 45 | D8: =IF(Fin_Activities!$A8="","",Fin_Activities!J8) -> 75 | E8: =IF(Fin_Activities!$A8="","",Fin_Activities!H8) -> 256 | F8: =IF(OR($A8="",$E8=0),0,IF($C8<=0,IF(AND($B8>=(F$5-1)*30,$B8<F$5*30),$E8,0),MAX(0,MIN($D8,F$5*30)-MAX($B8,(F$5-1)*30))/$C8*$E8)) -> 0 | G8: =IF(OR($A8="",$E8=0),0,IF($C8<=0,IF(AND($B8>=(G$5-1)*30,$B8<G$5*30),$E8,0),MAX(0,MIN($D8,G$5*30)-MAX($B8,(G$5-1)*30))/$C8*$E8)) -> 170.66667 | H8: =IF(OR($A8="",$E8=0),0,IF($C8<=0,IF(AND($B8>=(H$5-1)*30,$B8<H$5*30),$E8,0),MAX(0,MIN($D8,H$5*30)-MAX($B8,(H$5-1)*30))/$C8*$E8)) -> 85.333333 | I8: =IF(OR($A8="",$E8=0),0,IF($C8<=0,IF(AND($B8>=(I$5-1)*30,$B8<I$5*30),$E8,0),MAX(0,MIN($D8,I$5*30)-MAX($B8,(I$5-1)*30))/$C8*$E8)) -> 0 | J8: =IF(OR($A8="",$E8=0),0,IF($C8<=0,IF(AND($B8>=(J$5-1)*30,$B8<J$5*30),$E8,0),MAX(0,MIN($D8,J$5*30)-MAX($B8,(J$5-1)*30))/$C8*$E8)) -> 0 | K8: =IF(OR($A8="",$E8=0),0,IF($C8<=0,IF(AND($B8>=(K$5-1)*30,$B8<K$5*30),$E8,0),MAX(0,MIN($D8,K$5*30)-MAX($B8,(K$5-1)*30))/$C8*$E8)) -> 0 | L8: =IF(OR($A8="",$E8=0),0,IF($C8<=0,IF(AND($B8>=(L$5-1)*30,$B8<L$5*30),$E8,0),MAX(0,MIN($D8,L$5*30)-MAX($B8,(L$5-1)*30))/$C8*$E8)) -> 0 | M8: =IF(OR($A8="",$E8=0),0,IF($C8<=0,IF(AND($B8>=(M$5-1)*30,$B8<M$5*30),$E8,0),MAX(0,MIN($D8,M$5*30)-MAX($B8,(M$5-1)*30))/$C8*$E8)) -> 0 | ... BM8: =IF(OR($A8="",$E8=0),0,IF($C8<=0,IF(AND($B8>=(BM$5-1)*30,$B8<BM$5*30),$E8,0),MAX(0,MIN($D8,BM$5*30)-MAX($B8,(BM$5-1)*30))/$C8*$E8)) -> 0
A9: =IF(Fin_Activities!$A9="","",Fin_Activities!A9) -> A04 | B9: =IF(Fin_Activities!$A9="","",Fin_Activities!I9) -> 75 | C9: =IF(Fin_Activities!$A9="","",Fin_Activities!G9) -> 15 | D9: =IF(Fin_Activities!$A9="","",Fin_Activities!J9) -> 90 | E9: =IF(Fin_Activities!$A9="","",Fin_Activities!H9) -> 49.5 | F9: =IF(OR($A9="",$E9=0),0,IF($C9<=0,IF(AND($B9>=(F$5-1)*30,$B9<F$5*30),$E9,0),MAX(0,MIN($D9,F$5*30)-MAX($B9,(F$5-1)*30))/$C9*$E9)) -> 0 | G9: =IF(OR($A9="",$E9=0),0,IF($C9<=0,IF(AND($B9>=(G$5-1)*30,$B9<G$5*30),$E9,0),MAX(0,MIN($D9,G$5*30)-MAX($B9,(G$5-1)*30))/$C9*$E9)) -> 0 | H9: =IF(OR($A9="",$E9=0),0,IF($C9<=0,IF(AND($B9>=(H$5-1)*30,$B9<H$5*30),$E9,0),MAX(0,MIN($D9,H$5*30)-MAX($B9,(H$5-1)*30))/$C9*$E9)) -> 49.5 | I9: =IF(OR($A9="",$E9=0),0,IF($C9<=0,IF(AND($B9>=(I$5-1)*30,$B9<I$5*30),$E9,0),MAX(0,MIN($D9,I$5*30)-MAX($B9,(I$5-1)*30))/$C9*$E9)) -> 0 | J9: =IF(OR($A9="",$E9=0),0,IF($C9<=0,IF(AND($B9>=(J$5-1)*30,$B9<J$5*30),$E9,0),MAX(0,MIN($D9,J$5*30)-MAX($B9,(J$5-1)*30))/$C9*$E9)) -> 0 | K9: =IF(OR($A9="",$E9=0),0,IF($C9<=0,IF(AND($B9>=(K$5-1)*30,$B9<K$5*30),$E9,0),MAX(0,MIN($D9,K$5*30)-MAX($B9,(K$5-1)*30))/$C9*$E9)) -> 0 | L9: =IF(OR($A9="",$E9=0),0,IF($C9<=0,IF(AND($B9>=(L$5-1)*30,$B9<L$5*30),$E9,0),MAX(0,MIN($D9,L$5*30)-MAX($B9,(L$5-1)*30))/$C9*$E9)) -> 0 | M9: =IF(OR($A9="",$E9=0),0,IF($C9<=0,IF(AND($B9>=(M$5-1)*30,$B9<M$5*30),$E9,0),MAX(0,MIN($D9,M$5*30)-MAX($B9,(M$5-1)*30))/$C9*$E9)) -> 0 | ... BM9: =IF(OR($A9="",$E9=0),0,IF($C9<=0,IF(AND($B9>=(BM$5-1)*30,$B9<BM$5*30),$E9,0),MAX(0,MIN($D9,BM$5*30)-MAX($B9,(BM$5-1)*30))/$C9*$E9)) -> 0
A10: =IF(Fin_Activities!$A10="","",Fin_Activities!A10) -> A05 | B10: =IF(Fin_Activities!$A10="","",Fin_Activities!I10) -> 90 | C10: =IF(Fin_Activities!$A10="","",Fin_Activities!G10) -> 30 | D10: =IF(Fin_Activities!$A10="","",Fin_Activities!J10) -> 120 | E10: =IF(Fin_Activities!$A10="","",Fin_Activities!H10) -> 183 | F10: =IF(OR($A10="",$E10=0),0,IF($C10<=0,IF(AND($B10>=(F$5-1)*30,$B10<F$5*30),$E10,0),MAX(0,MIN($D10,F$5*30)-MAX($B10,(F$5-1)*30))/$C10*$E10)) -> 0 | G10: =IF(OR($A10="",$E10=0),0,IF($C10<=0,IF(AND($B10>=(G$5-1)*30,$B10<G$5*30),$E10,0),MAX(0,MIN($D10,G$5*30)-MAX($B10,(G$5-1)*30))/$C10*$E10)) -> 0 | H10: =IF(OR($A10="",$E10=0),0,IF($C10<=0,IF(AND($B10>=(H$5-1)*30,$B10<H$5*30),$E10,0),MAX(0,MIN($D10,H$5*30)-MAX($B10,(H$5-1)*30))/$C10*$E10)) -> 0 | I10: =IF(OR($A10="",$E10=0),0,IF($C10<=0,IF(AND($B10>=(I$5-1)*30,$B10<I$5*30),$E10,0),MAX(0,MIN($D10,I$5*30)-MAX($B10,(I$5-1)*30))/$C10*$E10)) -> 183 | J10: =IF(OR($A10="",$E10=0),0,IF($C10<=0,IF(AND($B10>=(J$5-1)*30,$B10<J$5*30),$E10,0),MAX(0,MIN($D10,J$5*30)-MAX($B10,(J$5-1)*30))/$C10*$E10)) -> 0 | K10: =IF(OR($A10="",$E10=0),0,IF($C10<=0,IF(AND($B10>=(K$5-1)*30,$B10<K$5*30),$E10,0),MAX(0,MIN($D10,K$5*30)-MAX($B10,(K$5-1)*30))/$C10*$E10)) -> 0 | L10: =IF(OR($A10="",$E10=0),0,IF($C10<=0,IF(AND($B10>=(L$5-1)*30,$B10<L$5*30),$E10,0),MAX(0,MIN($D10,L$5*30)-MAX($B10,(L$5-1)*30))/$C10*$E10)) -> 0 | M10: =IF(OR($A10="",$E10=0),0,IF($C10<=0,IF(AND($B10>=(M$5-1)*30,$B10<M$5*30),$E10,0),MAX(0,MIN($D10,M$5*30)-MAX($B10,(M$5-1)*30))/$C10*$E10)) -> 0 | ... BM10: =IF(OR($A10="",$E10=0),0,IF($C10<=0,IF(AND($B10>=(BM$5-1)*30,$B10<BM$5*30),$E10,0),MAX(0,MIN($D10,BM$5*30)-MAX($B10,(BM$5-1)*30))/$C10*$E10)) -> 0
A11: =IF(Fin_Activities!$A11="","",Fin_Activities!A11) -> A06 | B11: =IF(Fin_Activities!$A11="","",Fin_Activities!I11) -> 120 | C11: =IF(Fin_Activities!$A11="","",Fin_Activities!G11) -> 20 | D11: =IF(Fin_Activities!$A11="","",Fin_Activities!J11) -> 140 | E11: =IF(Fin_Activities!$A11="","",Fin_Activities!H11) -> 72 | F11: =IF(OR($A11="",$E11=0),0,IF($C11<=0,IF(AND($B11>=(F$5-1)*30,$B11<F$5*30),$E11,0),MAX(0,MIN($D11,F$5*30)-MAX($B11,(F$5-1)*30))/$C11*$E11)) -> 0 | G11: =IF(OR($A11="",$E11=0),0,IF($C11<=0,IF(AND($B11>=(G$5-1)*30,$B11<G$5*30),$E11,0),MAX(0,MIN($D11,G$5*30)-MAX($B11,(G$5-1)*30))/$C11*$E11)) -> 0 | H11: =IF(OR($A11="",$E11=0),0,IF($C11<=0,IF(AND($B11>=(H$5-1)*30,$B11<H$5*30),$E11,0),MAX(0,MIN($D11,H$5*30)-MAX($B11,(H$5-1)*30))/$C11*$E11)) -> 0 | I11: =IF(OR($A11="",$E11=0),0,IF($C11<=0,IF(AND($B11>=(I$5-1)*30,$B11<I$5*30),$E11,0),MAX(0,MIN($D11,I$5*30)-MAX($B11,(I$5-1)*30))/$C11*$E11)) -> 0 | J11: =IF(OR($A11="",$E11=0),0,IF($C11<=0,IF(AND($B11>=(J$5-1)*30,$B11<J$5*30),$E11,0),MAX(0,MIN($D11,J$5*30)-MAX($B11,(J$5-1)*30))/$C11*$E11)) -> 72 | K11: =IF(OR($A11="",$E11=0),0,IF($C11<=0,IF(AND($B11>=(K$5-1)*30,$B11<K$5*30),$E11,0),MAX(0,MIN($D11,K$5*30)-MAX($B11,(K$5-1)*30))/$C11*$E11)) -> 0 | L11: =IF(OR($A11="",$E11=0),0,IF($C11<=0,IF(AND($B11>=(L$5-1)*30,$B11<L$5*30),$E11,0),MAX(0,MIN($D11,L$5*30)-MAX($B11,(L$5-1)*30))/$C11*$E11)) -> 0 | M11: =IF(OR($A11="",$E11=0),0,IF($C11<=0,IF(AND($B11>=(M$5-1)*30,$B11<M$5*30),$E11,0),MAX(0,MIN($D11,M$5*30)-MAX($B11,(M$5-1)*30))/$C11*$E11)) -> 0 | ... BM11: =IF(OR($A11="",$E11=0),0,IF($C11<=0,IF(AND($B11>=(BM$5-1)*30,$B11<BM$5*30),$E11,0),MAX(0,MIN($D11,BM$5*30)-MAX($B11,(BM$5-1)*30))/$C11*$E11)) -> 0
A12: =IF(Fin_Activities!$A12="","",Fin_Activities!A12) -> A07 | B12: =IF(Fin_Activities!$A12="","",Fin_Activities!I12) -> 140 | C12: =IF(Fin_Activities!$A12="","",Fin_Activities!G12) -> 90 | D12: =IF(Fin_Activities!$A12="","",Fin_Activities!J12) -> 230 | E12: =IF(Fin_Activities!$A12="","",Fin_Activities!H12) -> 434 | F12: =IF(OR($A12="",$E12=0),0,IF($C12<=0,IF(AND($B12>=(F$5-1)*30,$B12<F$5*30),$E12,0),MAX(0,MIN($D12,F$5*30)-MAX($B12,(F$5-1)*30))/$C12*$E12)) -> 0 | G12: =IF(OR($A12="",$E12=0),0,IF($C12<=0,IF(AND($B12>=(G$5-1)*30,$B12<G$5*30),$E12,0),MAX(0,MIN($D12,G$5*30)-MAX($B12,(G$5-1)*30))/$C12*$E12)) -> 0 | H12: =IF(OR($A12="",$E12=0),0,IF($C12<=0,IF(AND($B12>=(H$5-1)*30,$B12<H$5*30),$E12,0),MAX(0,MIN($D12,H$5*30)-MAX($B12,(H$5-1)*30))/$C12*$E12)) -> 0 | I12: =IF(OR($A12="",$E12=0),0,IF($C12<=0,IF(AND($B12>=(I$5-1)*30,$B12<I$5*30),$E12,0),MAX(0,MIN($D12,I$5*30)-MAX($B12,(I$5-1)*30))/$C12*$E12)) -> 0 | J12: =IF(OR($A12="",$E12=0),0,IF($C12<=0,IF(AND($B12>=(J$5-1)*30,$B12<J$5*30),$E12,0),MAX(0,MIN($D12,J$5*30)-MAX($B12,(J$5-1)*30))/$C12*$E12)) -> 48.222222 | K12: =IF(OR($A12="",$E12=0),0,IF($C12<=0,IF(AND($B12>=(K$5-1)*30,$B12<K$5*30),$E12,0),MAX(0,MIN($D12,K$5*30)-MAX($B12,(K$5-1)*30))/$C12*$E12)) -> 144.66667 | L12: =IF(OR($A12="",$E12=0),0,IF($C12<=0,IF(AND($B12>=(L$5-1)*30,$B12<L$5*30),$E12,0),MAX(0,MIN($D12,L$5*30)-MAX($B12,(L$5-1)*30))/$C12*$E12)) -> 144.66667 | M12: =IF(OR($A12="",$E12=0),0,IF($C12<=0,IF(AND($B12>=(M$5-1)*30,$B12<M$5*30),$E12,0),MAX(0,MIN($D12,M$5*30)-MAX($B12,(M$5-1)*30))/$C12*$E12)) -> 96.444444 | ... BM12: =IF(OR($A12="",$E12=0),0,IF($C12<=0,IF(AND($B12>=(BM$5-1)*30,$B12<BM$5*30),$E12,0),MAX(0,MIN($D12,BM$5*30)-MAX($B12,(BM$5-1)*30))/$C12*$E12)) -> 0
A13: =IF(Fin_Activities!$A13="","",Fin_Activities!A13) -> A08 | B13: =IF(Fin_Activities!$A13="","",Fin_Activities!I13) -> 230 | C13: =IF(Fin_Activities!$A13="","",Fin_Activities!G13) -> 85 | D13: =IF(Fin_Activities!$A13="","",Fin_Activities!J13) -> 315 | E13: =IF(Fin_Activities!$A13="","",Fin_Activities!H13) -> 431 | F13: =IF(OR($A13="",$E13=0),0,IF($C13<=0,IF(AND($B13>=(F$5-1)*30,$B13<F$5*30),$E13,0),MAX(0,MIN($D13,F$5*30)-MAX($B13,(F$5-1)*30))/$C13*$E13)) -> 0 | G13: =IF(OR($A13="",$E13=0),0,IF($C13<=0,IF(AND($B13>=(G$5-1)*30,$B13<G$5*30),$E13,0),MAX(0,MIN($D13,G$5*30)-MAX($B13,(G$5-1)*30))/$C13*$E13)) -> 0 | H13: =IF(OR($A13="",$E13=0),0,IF($C13<=0,IF(AND($B13>=(H$5-1)*30,$B13<H$5*30),$E13,0),MAX(0,MIN($D13,H$5*30)-MAX($B13,(H$5-1)*30))/$C13*$E13)) -> 0 | I13: =IF(OR($A13="",$E13=0),0,IF($C13<=0,IF(AND($B13>=(I$5-1)*30,$B13<I$5*30),$E13,0),MAX(0,MIN($D13,I$5*30)-MAX($B13,(I$5-1)*30))/$C13*$E13)) -> 0 | J13: =IF(OR($A13="",$E13=0),0,IF($C13<=0,IF(AND($B13>=(J$5-1)*30,$B13<J$5*30),$E13,0),MAX(0,MIN($D13,J$5*30)-MAX($B13,(J$5-1)*30))/$C13*$E13)) -> 0 | K13: =IF(OR($A13="",$E13=0),0,IF($C13<=0,IF(AND($B13>=(K$5-1)*30,$B13<K$5*30),$E13,0),MAX(0,MIN($D13,K$5*30)-MAX($B13,(K$5-1)*30))/$C13*$E13)) -> 0 | L13: =IF(OR($A13="",$E13=0),0,IF($C13<=0,IF(AND($B13>=(L$5-1)*30,$B13<L$5*30),$E13,0),MAX(0,MIN($D13,L$5*30)-MAX($B13,(L$5-1)*30))/$C13*$E13)) -> 0 | M13: =IF(OR($A13="",$E13=0),0,IF($C13<=0,IF(AND($B13>=(M$5-1)*30,$B13<M$5*30),$E13,0),MAX(0,MIN($D13,M$5*30)-MAX($B13,(M$5-1)*30))/$C13*$E13)) -> 50.705882 | ... BM13: =IF(OR($A13="",$E13=0),0,IF($C13<=0,IF(AND($B13>=(BM$5-1)*30,$B13<BM$5*30),$E13,0),MAX(0,MIN($D13,BM$5*30)-MAX($B13,(BM$5-1)*30))/$C13*$E13)) -> 0
A14: =IF(Fin_Activities!$A14="","",Fin_Activities!A14) -> A09 | B14: =IF(Fin_Activities!$A14="","",Fin_Activities!I14) -> 230 | C14: =IF(Fin_Activities!$A14="","",Fin_Activities!G14) -> 60 | D14: =IF(Fin_Activities!$A14="","",Fin_Activities!J14) -> 290 | E14: =IF(Fin_Activities!$A14="","",Fin_Activities!H14) -> 113 | F14: =IF(OR($A14="",$E14=0),0,IF($C14<=0,IF(AND($B14>=(F$5-1)*30,$B14<F$5*30),$E14,0),MAX(0,MIN($D14,F$5*30)-MAX($B14,(F$5-1)*30))/$C14*$E14)) -> 0 | G14: =IF(OR($A14="",$E14=0),0,IF($C14<=0,IF(AND($B14>=(G$5-1)*30,$B14<G$5*30),$E14,0),MAX(0,MIN($D14,G$5*30)-MAX($B14,(G$5-1)*30))/$C14*$E14)) -> 0 | H14: =IF(OR($A14="",$E14=0),0,IF($C14<=0,IF(AND($B14>=(H$5-1)*30,$B14<H$5*30),$E14,0),MAX(0,MIN($D14,H$5*30)-MAX($B14,(H$5-1)*30))/$C14*$E14)) -> 0 | I14: =IF(OR($A14="",$E14=0),0,IF($C14<=0,IF(AND($B14>=(I$5-1)*30,$B14<I$5*30),$E14,0),MAX(0,MIN($D14,I$5*30)-MAX($B14,(I$5-1)*30))/$C14*$E14)) -> 0 | J14: =IF(OR($A14="",$E14=0),0,IF($C14<=0,IF(AND($B14>=(J$5-1)*30,$B14<J$5*30),$E14,0),MAX(0,MIN($D14,J$5*30)-MAX($B14,(J$5-1)*30))/$C14*$E14)) -> 0 | K14: =IF(OR($A14="",$E14=0),0,IF($C14<=0,IF(AND($B14>=(K$5-1)*30,$B14<K$5*30),$E14,0),MAX(0,MIN($D14,K$5*30)-MAX($B14,(K$5-1)*30))/$C14*$E14)) -> 0 | L14: =IF(OR($A14="",$E14=0),0,IF($C14<=0,IF(AND($B14>=(L$5-1)*30,$B14<L$5*30),$E14,0),MAX(0,MIN($D14,L$5*30)-MAX($B14,(L$5-1)*30))/$C14*$E14)) -> 0 | M14: =IF(OR($A14="",$E14=0),0,IF($C14<=0,IF(AND($B14>=(M$5-1)*30,$B14<M$5*30),$E14,0),MAX(0,MIN($D14,M$5*30)-MAX($B14,(M$5-1)*30))/$C14*$E14)) -> 18.833333 | ... BM14: =IF(OR($A14="",$E14=0),0,IF($C14<=0,IF(AND($B14>=(BM$5-1)*30,$B14<BM$5*30),$E14,0),MAX(0,MIN($D14,BM$5*30)-MAX($B14,(BM$5-1)*30))/$C14*$E14)) -> 0
A15: =IF(Fin_Activities!$A15="","",Fin_Activities!A15) -> A10 | B15: =IF(Fin_Activities!$A15="","",Fin_Activities!I15) -> 315 | C15: =IF(Fin_Activities!$A15="","",Fin_Activities!G15) -> 55 | D15: =IF(Fin_Activities!$A15="","",Fin_Activities!J15) -> 370 | E15: =IF(Fin_Activities!$A15="","",Fin_Activities!H15) -> 112.75 | F15: =IF(OR($A15="",$E15=0),0,IF($C15<=0,IF(AND($B15>=(F$5-1)*30,$B15<F$5*30),$E15,0),MAX(0,MIN($D15,F$5*30)-MAX($B15,(F$5-1)*30))/$C15*$E15)) -> 0 | G15: =IF(OR($A15="",$E15=0),0,IF($C15<=0,IF(AND($B15>=(G$5-1)*30,$B15<G$5*30),$E15,0),MAX(0,MIN($D15,G$5*30)-MAX($B15,(G$5-1)*30))/$C15*$E15)) -> 0 | H15: =IF(OR($A15="",$E15=0),0,IF($C15<=0,IF(AND($B15>=(H$5-1)*30,$B15<H$5*30),$E15,0),MAX(0,MIN($D15,H$5*30)-MAX($B15,(H$5-1)*30))/$C15*$E15)) -> 0 | I15: =IF(OR($A15="",$E15=0),0,IF($C15<=0,IF(AND($B15>=(I$5-1)*30,$B15<I$5*30),$E15,0),MAX(0,MIN($D15,I$5*30)-MAX($B15,(I$5-1)*30))/$C15*$E15)) -> 0 | J15: =IF(OR($A15="",$E15=0),0,IF($C15<=0,IF(AND($B15>=(J$5-1)*30,$B15<J$5*30),$E15,0),MAX(0,MIN($D15,J$5*30)-MAX($B15,(J$5-1)*30))/$C15*$E15)) -> 0 | K15: =IF(OR($A15="",$E15=0),0,IF($C15<=0,IF(AND($B15>=(K$5-1)*30,$B15<K$5*30),$E15,0),MAX(0,MIN($D15,K$5*30)-MAX($B15,(K$5-1)*30))/$C15*$E15)) -> 0 | L15: =IF(OR($A15="",$E15=0),0,IF($C15<=0,IF(AND($B15>=(L$5-1)*30,$B15<L$5*30),$E15,0),MAX(0,MIN($D15,L$5*30)-MAX($B15,(L$5-1)*30))/$C15*$E15)) -> 0 | M15: =IF(OR($A15="",$E15=0),0,IF($C15<=0,IF(AND($B15>=(M$5-1)*30,$B15<M$5*30),$E15,0),MAX(0,MIN($D15,M$5*30)-MAX($B15,(M$5-1)*30))/$C15*$E15)) -> 0 | ... BM15: =IF(OR($A15="",$E15=0),0,IF($C15<=0,IF(AND($B15>=(BM$5-1)*30,$B15<BM$5*30),$E15,0),MAX(0,MIN($D15,BM$5*30)-MAX($B15,(BM$5-1)*30))/$C15*$E15)) -> 0
A16: =IF(Fin_Activities!$A16="","",Fin_Activities!A16) -> A11 | B16: =IF(Fin_Activities!$A16="","",Fin_Activities!I16) -> 290 | C16: =IF(Fin_Activities!$A16="","",Fin_Activities!G16) -> 45 | D16: =IF(Fin_Activities!$A16="","",Fin_Activities!J16) -> 335 | E16: =IF(Fin_Activities!$A16="","",Fin_Activities!H16) -> 61.35 | F16: =IF(OR($A16="",$E16=0),0,IF($C16<=0,IF(AND($B16>=(F$5-1)*30,$B16<F$5*30),$E16,0),MAX(0,MIN($D16,F$5*30)-MAX($B16,(F$5-1)*30))/$C16*$E16)) -> 0 | G16: =IF(OR($A16="",$E16=0),0,IF($C16<=0,IF(AND($B16>=(G$5-1)*30,$B16<G$5*30),$E16,0),MAX(0,MIN($D16,G$5*30)-MAX($B16,(G$5-1)*30))/$C16*$E16)) -> 0 | H16: =IF(OR($A16="",$E16=0),0,IF($C16<=0,IF(AND($B16>=(H$5-1)*30,$B16<H$5*30),$E16,0),MAX(0,MIN($D16,H$5*30)-MAX($B16,(H$5-1)*30))/$C16*$E16)) -> 0 | I16: =IF(OR($A16="",$E16=0),0,IF($C16<=0,IF(AND($B16>=(I$5-1)*30,$B16<I$5*30),$E16,0),MAX(0,MIN($D16,I$5*30)-MAX($B16,(I$5-1)*30))/$C16*$E16)) -> 0 | J16: =IF(OR($A16="",$E16=0),0,IF($C16<=0,IF(AND($B16>=(J$5-1)*30,$B16<J$5*30),$E16,0),MAX(0,MIN($D16,J$5*30)-MAX($B16,(J$5-1)*30))/$C16*$E16)) -> 0 | K16: =IF(OR($A16="",$E16=0),0,IF($C16<=0,IF(AND($B16>=(K$5-1)*30,$B16<K$5*30),$E16,0),MAX(0,MIN($D16,K$5*30)-MAX($B16,(K$5-1)*30))/$C16*$E16)) -> 0 | L16: =IF(OR($A16="",$E16=0),0,IF($C16<=0,IF(AND($B16>=(L$5-1)*30,$B16<L$5*30),$E16,0),MAX(0,MIN($D16,L$5*30)-MAX($B16,(L$5-1)*30))/$C16*$E16)) -> 0 | M16: =IF(OR($A16="",$E16=0),0,IF($C16<=0,IF(AND($B16>=(M$5-1)*30,$B16<M$5*30),$E16,0),MAX(0,MIN($D16,M$5*30)-MAX($B16,(M$5-1)*30))/$C16*$E16)) -> 0 | ... BM16: =IF(OR($A16="",$E16=0),0,IF($C16<=0,IF(AND($B16>=(BM$5-1)*30,$B16<BM$5*30),$E16,0),MAX(0,MIN($D16,BM$5*30)-MAX($B16,(BM$5-1)*30))/$C16*$E16)) -> 0
A17: =IF(Fin_Activities!$A17="","",Fin_Activities!A17) -> A12 | B17: =IF(Fin_Activities!$A17="","",Fin_Activities!I17) -> 370 | C17: =IF(Fin_Activities!$A17="","",Fin_Activities!G17) -> 45 | D17: =IF(Fin_Activities!$A17="","",Fin_Activities!J17) -> 415 | E17: =IF(Fin_Activities!$A17="","",Fin_Activities!H17) -> 61.35 | F17: =IF(OR($A17="",$E17=0),0,IF($C17<=0,IF(AND($B17>=(F$5-1)*30,$B17<F$5*30),$E17,0),MAX(0,MIN($D17,F$5*30)-MAX($B17,(F$5-1)*30))/$C17*$E17)) -> 0 | G17: =IF(OR($A17="",$E17=0),0,IF($C17<=0,IF(AND($B17>=(G$5-1)*30,$B17<G$5*30),$E17,0),MAX(0,MIN($D17,G$5*30)-MAX($B17,(G$5-1)*30))/$C17*$E17)) -> 0 | H17: =IF(OR($A17="",$E17=0),0,IF($C17<=0,IF(AND($B17>=(H$5-1)*30,$B17<H$5*30),$E17,0),MAX(0,MIN($D17,H$5*30)-MAX($B17,(H$5-1)*30))/$C17*$E17)) -> 0 | I17: =IF(OR($A17="",$E17=0),0,IF($C17<=0,IF(AND($B17>=(I$5-1)*30,$B17<I$5*30),$E17,0),MAX(0,MIN($D17,I$5*30)-MAX($B17,(I$5-1)*30))/$C17*$E17)) -> 0 | J17: =IF(OR($A17="",$E17=0),0,IF($C17<=0,IF(AND($B17>=(J$5-1)*30,$B17<J$5*30),$E17,0),MAX(0,MIN($D17,J$5*30)-MAX($B17,(J$5-1)*30))/$C17*$E17)) -> 0 | K17: =IF(OR($A17="",$E17=0),0,IF($C17<=0,IF(AND($B17>=(K$5-1)*30,$B17<K$5*30),$E17,0),MAX(0,MIN($D17,K$5*30)-MAX($B17,(K$5-1)*30))/$C17*$E17)) -> 0 | L17: =IF(OR($A17="",$E17=0),0,IF($C17<=0,IF(AND($B17>=(L$5-1)*30,$B17<L$5*30),$E17,0),MAX(0,MIN($D17,L$5*30)-MAX($B17,(L$5-1)*30))/$C17*$E17)) -> 0 | M17: =IF(OR($A17="",$E17=0),0,IF($C17<=0,IF(AND($B17>=(M$5-1)*30,$B17<M$5*30),$E17,0),MAX(0,MIN($D17,M$5*30)-MAX($B17,(M$5-1)*30))/$C17*$E17)) -> 0 | ... BM17: =IF(OR($A17="",$E17=0),0,IF($C17<=0,IF(AND($B17>=(BM$5-1)*30,$B17<BM$5*30),$E17,0),MAX(0,MIN($D17,BM$5*30)-MAX($B17,(BM$5-1)*30))/$C17*$E17)) -> 0
... A45: =IF(Fin_Activities!$A45="","",Fin_Activities!A45) | B45: =IF(Fin_Activities!$A45="","",Fin_Activities!I45) | C45: =IF(Fin_Activities!$A45="","",Fin_Activities!G45) | D45: =IF(Fin_Activities!$A45="","",Fin_Activities!J45) | E45: =IF(Fin_Activities!$A45="","",Fin_Activities!H45) | F45: =IF(OR($A45="",$E45=0),0,IF($C45<=0,IF(AND($B45>=(F$5-1)*30,$B45<F$5*30),$E45,0),MAX(0,MIN($D45,F$5*30)-MAX($B45,(F$5-1)*30))/$C45*$E45)) -> 0 | G45: =IF(OR($A45="",$E45=0),0,IF($C45<=0,IF(AND($B45>=(G$5-1)*30,$B45<G$5*30),$E45,0),MAX(0,MIN($D45,G$5*30)-MAX($B45,(G$5-1)*30))/$C45*$E45)) -> 0 | H45: =IF(OR($A45="",$E45=0),0,IF($C45<=0,IF(AND($B45>=(H$5-1)*30,$B45<H$5*30),$E45,0),MAX(0,MIN($D45,H$5*30)-MAX($B45,(H$5-1)*30))/$C45*$E45)) -> 0 | I45: =IF(OR($A45="",$E45=0),0,IF($C45<=0,IF(AND($B45>=(I$5-1)*30,$B45<I$5*30),$E45,0),MAX(0,MIN($D45,I$5*30)-MAX($B45,(I$5-1)*30))/$C45*$E45)) -> 0 | J45: =IF(OR($A45="",$E45=0),0,IF($C45<=0,IF(AND($B45>=(J$5-1)*30,$B45<J$5*30),$E45,0),MAX(0,MIN($D45,J$5*30)-MAX($B45,(J$5-1)*30))/$C45*$E45)) -> 0 | K45: =IF(OR($A45="",$E45=0),0,IF($C45<=0,IF(AND($B45>=(K$5-1)*30,$B45<K$5*30),$E45,0),MAX(0,MIN($D45,K$5*30)-MAX($B45,(K$5-1)*30))/$C45*$E45)) -> 0 | L45: =IF(OR($A45="",$E45=0),0,IF($C45<=0,IF(AND($B45>=(L$5-1)*30,$B45<L$5*30),$E45,0),MAX(0,MIN($D45,L$5*30)-MAX($B45,(L$5-1)*30))/$C45*$E45)) -> 0 | M45: =IF(OR($A45="",$E45=0),0,IF($C45<=0,IF(AND($B45>=(M$5-1)*30,$B45<M$5*30),$E45,0),MAX(0,MIN($D45,M$5*30)-MAX($B45,(M$5-1)*30))/$C45*$E45)) -> 0 | ... BM45: =IF(OR($A45="",$E45=0),0,IF($C45<=0,IF(AND($B45>=(BM$5-1)*30,$B45<BM$5*30),$E45,0),MAX(0,MIN($D45,BM$5*30)-MAX($B45,(BM$5-1)*30))/$C45*$E45)) -> 0
A46: Total | F46: =SUM(F6:F45) -> 51.2 | G46: =SUM(G6:G45) -> 170.66667 | H46: =SUM(H6:H45) -> 134.83333 | I46: =SUM(I6:I45) -> 183 | J46: =SUM(J6:J45) -> 120.22222 | K46: =SUM(K6:K45) -> 144.66667 | L46: =SUM(L6:L45) -> 144.66667 | M46: =SUM(M6:M45) -> 165.98366 | ... BM46: =SUM(BM6:BM45) -> 0

Sheet Fin_CashFlow
A1: T15-T21: Monthly cash flow, debt, NPV and IRR
A2: Month 0 = start (land). Month k = days (k-1)*30 to k*30. Rules match docs/NEW_FEATURES_GUIDE.md section 2.
A4: Month | B4: 0 | C4: 1 | D4: 2 | E4: 3 | F4: 4 | G4: 5 | H4: 6 | I4: 7 | J4: 8 | K4: 9 | L4: 10 | M4: 11 | N4: 12 | O4: 13 | P4: 14 | Q4: 15 | R4: 16 | S4: 17 | T4: 18 | U4: 19 | V4: 20 | W4: 21 | X4: 22 | Y4: 23 | Z4: 24 | AA4: 25 | AB4: 26 | AC4: 27 | AD4: 28 | AE4: 29 | AF4: 30 | AG4: 31 | AH4: 32 | AI4: 33 | AJ4: 34 | AK4: 35 | AL4: 36 | AM4: 37 | AN4: 38 | AO4: 39 | AP4: 40 | AQ4: 41 | AR4: 42 | AS4: 43 | AT4: 44 | AU4: 45 | AV4: 46 | AW4: 47 | AX4: 48 | AY4: 49 | AZ4: 50 | BA4: 51 | BB4: 52 | BC4: 53 | BD4: 54 | BE4: 55 | BF4: 56 | BG4: 57 | BH4: 58 | BI4: 59 | BJ4: 60
A5: Upfront (land + approvals) | B5: =IF(B$4=0,Fin_Inputs!$C$5+Fin_Inputs!$C$6,0) -> 2650 | C5: =IF(C$4=0,Fin_Inputs!$C$5+Fin_Inputs!$C$6,0) -> 0 | D5: =IF(D$4=0,Fin_Inputs!$C$5+Fin_Inputs!$C$6,0) -> 0 | E5: =IF(E$4=0,Fin_Inputs!$C$5+Fin_Inputs!$C$6,0) -> 0 | F5: =IF(F$4=0,Fin_Inputs!$C$5+Fin_Inputs!$C$6,0) -> 0 | G5: =IF(G$4=0,Fin_Inputs!$C$5+Fin_Inputs!$C$6,0) -> 0 | H5: =IF(H$4=0,Fin_Inputs!$C$5+Fin_Inputs!$C$6,0) -> 0 | I5: =IF(I$4=0,Fin_Inputs!$C$5+Fin_Inputs!$C$6,0) -> 0 | ... BJ5: =IF(BJ$4=0,Fin_Inputs!$C$5+Fin_Inputs!$C$6,0) -> 0
A6: Construction spend | B6: =0 -> 0 | C6: =Fin_Spread!F46 -> 51.2 | D6: =Fin_Spread!G46 -> 170.66667 | E6: =Fin_Spread!H46 -> 134.83333 | F6: =Fin_Spread!I46 -> 183 | G6: =Fin_Spread!J46 -> 120.22222 | H6: =Fin_Spread!K46 -> 144.66667 | I6: =Fin_Spread!L46 -> 144.66667 | J6: =Fin_Spread!M46 -> 165.98366 | ... BJ6: =Fin_Spread!BM46 -> 0
A7: Overheads | B7: =0 -> 0 | C7: =Fin_Inputs!$C$16*Fin_Inputs!$C$21*MAX(0,MIN(30,Fin_Activities!$C$47-(C$4-1)*30))/30 -> 12 | D7: =Fin_Inputs!$C$16*Fin_Inputs!$C$21*MAX(0,MIN(30,Fin_Activities!$C$47-(D$4-1)*30))/30 -> 12 | E7: =Fin_Inputs!$C$16*Fin_Inputs!$C$21*MAX(0,MIN(30,Fin_Activities!$C$47-(E$4-1)*30))/30 -> 12 | F7: =Fin_Inputs!$C$16*Fin_Inputs!$C$21*MAX(0,MIN(30,Fin_Activities!$C$47-(F$4-1)*30))/30 -> 12 | G7: =Fin_Inputs!$C$16*Fin_Inputs!$C$21*MAX(0,MIN(30,Fin_Activities!$C$47-(G$4-1)*30))/30 -> 12 | H7: =Fin_Inputs!$C$16*Fin_Inputs!$C$21*MAX(0,MIN(30,Fin_Activities!$C$47-(H$4-1)*30))/30 -> 12 | I7: =Fin_Inputs!$C$16*Fin_Inputs!$C$21*MAX(0,MIN(30,Fin_Activities!$C$47-(I$4-1)*30))/30 -> 12 | J7: =Fin_Inputs!$C$16*Fin_Inputs!$C$21*MAX(0,MIN(30,Fin_Activities!$C$47-(J$4-1)*30))/30 -> 12 | ... BJ7: =Fin_Inputs!$C$16*Fin_Inputs!$C$21*MAX(0,MIN(30,Fin_Activities!$C$47-(BJ$4-1)*30))/30 -> 0
A8: Progress share | B8: =IF(SUM($B$6:$BJ$6)=0,0,B6/SUM($B$6:$BJ$6)) -> 0 | C8: =IF(SUM($B$6:$BJ$6)=0,0,C6/SUM($B$6:$BJ$6)) -> 0.014637563 | D8: =IF(SUM($B$6:$BJ$6)=0,0,D6/SUM($B$6:$BJ$6)) -> 0.048791877 | E8: =IF(SUM($B$6:$BJ$6)=0,0,E6/SUM($B$6:$BJ$6)) -> 0.038547489 | F8: =IF(SUM($B$6:$BJ$6)=0,0,F6/SUM($B$6:$BJ$6)) -> 0.052317852 | G8: =IF(SUM($B$6:$BJ$6)=0,0,G6/SUM($B$6:$BJ$6)) -> 0.03437032 | H8: =IF(SUM($B$6:$BJ$6)=0,0,H6/SUM($B$6:$BJ$6)) -> 0.041358739 | I8: =IF(SUM($B$6:$BJ$6)=0,0,I6/SUM($B$6:$BJ$6)) -> 0.041358739 | ... BJ8: =IF(SUM($B$6:$BJ$6)=0,0,BJ6/SUM($B$6:$BJ$6)) -> 0
A9: Presale collections | B9: =Fin_Inputs!$C$9*Fin_Inputs!$C$29*B8 -> 0 | C9: =Fin_Inputs!$C$9*Fin_Inputs!$C$29*C8 -> 37.545349 | D9: =Fin_Inputs!$C$9*Fin_Inputs!$C$29*D8 -> 125.15116 | E9: =Fin_Inputs!$C$9*Fin_Inputs!$C$29*E8 -> 98.874309 | F9: =Fin_Inputs!$C$9*Fin_Inputs!$C$29*F8 -> 134.19529 | G9: =Fin_Inputs!$C$9*Fin_Inputs!$C$29*G8 -> 88.15987 | H9: =Fin_Inputs!$C$9*Fin_Inputs!$C$29*H8 -> 106.08517 | I9: =Fin_Inputs!$C$9*Fin_Inputs!$C$29*I8 -> 106.08517 | ... BJ9: =Fin_Inputs!$C$9*Fin_Inputs!$C$29*BJ8 -> 0
A10: Later collections | B10: =IF(AND(B$4>Fin_Activities!$C$49,B$4<=Fin_Activities!$C$49+Fin_Inputs!$C$10),(1-Fin_Inputs!$C$9)*Fin_Inputs!$C$29/Fin_Inputs!$C$10,0) -> 0 | C10: =IF(AND(C$4>Fin_Activities!$C$49,C$4<=Fin_Activities!$C$49+Fin_Inputs!$C$10),(1-Fin_Inputs!$C$9)*Fin_Inputs!$C$29/Fin_Inputs!$C$10,0) -> 0 | D10: =IF(AND(D$4>Fin_Activities!$C$49,D$4<=Fin_Activities!$C$49+Fin_Inputs!$C$10),(1-Fin_Inputs!$C$9)*Fin_Inputs!$C$29/Fin_Inputs!$C$10,0) -> 0 | E10: =IF(AND(E$4>Fin_Activities!$C$49,E$4<=Fin_Activities!$C$49+Fin_Inputs!$C$10),(1-Fin_Inputs!$C$9)*Fin_Inputs!$C$29/Fin_Inputs!$C$10,0) -> 0 | F10: =IF(AND(F$4>Fin_Activities!$C$49,F$4<=Fin_Activities!$C$49+Fin_Inputs!$C$10),(1-Fin_Inputs!$C$9)*Fin_Inputs!$C$29/Fin_Inputs!$C$10,0) -> 0 | G10: =IF(AND(G$4>Fin_Activities!$C$49,G$4<=Fin_Activities!$C$49+Fin_Inputs!$C$10),(1-Fin_Inputs!$C$9)*Fin_Inputs!$C$29/Fin_Inputs!$C$10,0) -> 0 | H10: =IF(AND(H$4>Fin_Activities!$C$49,H$4<=Fin_Activities!$C$49+Fin_Inputs!$C$10),(1-Fin_Inputs!$C$9)*Fin_Inputs!$C$29/Fin_Inputs!$C$10,0) -> 0 | I10: =IF(AND(I$4>Fin_Activities!$C$49,I$4<=Fin_Activities!$C$49+Fin_Inputs!$C$10),(1-Fin_Inputs!$C$9)*Fin_Inputs!$C$29/Fin_Inputs!$C$10,0) -> 0 | ... BJ10: =IF(AND(BJ$4>Fin_Activities!$C$49,BJ$4<=Fin_Activities!$C$49+Fin_Inputs!$C$10),(1-Fin_Inputs!$C$9)*Fin_Inputs!$C$29/Fin_Inputs!$C$10,0) -> 0
A11: Total collections | B11: =B9+B10 -> 0 | C11: =C9+C10 -> 37.545349 | D11: =D9+D10 -> 125.15116 | E11: =E9+E10 -> 98.874309 | F11: =F9+F10 -> 134.19529 | G11: =G9+G10 -> 88.15987 | H11: =H9+H10 -> 106.08517 | I11: =I9+I10 -> 106.08517 | ... BJ11: =BJ9+BJ10 -> 0
A12: Brokerage | B12: =Fin_Inputs!$C$11*B11 -> 0 | C12: =Fin_Inputs!$C$11*C11 -> 0.75090699 | D12: =Fin_Inputs!$C$11*D11 -> 2.5030233 | E12: =Fin_Inputs!$C$11*E11 -> 1.9774862 | F12: =Fin_Inputs!$C$11*F11 -> 2.6839058 | G12: =Fin_Inputs!$C$11*G11 -> 1.7631974 | H12: =Fin_Inputs!$C$11*H11 -> 2.1217033 | I12: =Fin_Inputs!$C$11*I11 -> 2.1217033 | ... BJ12: =Fin_Inputs!$C$11*BJ11 -> 0
A13: Buyers' payments before this month | B13: =0 -> 0 | C13: =SUM($B$9:B9) -> 0 | D13: =SUM($B$9:C9) -> 37.545349 | E13: =SUM($B$9:D9) -> 162.69651 | F13: =SUM($B$9:E9) -> 261.57082 | G13: =SUM($B$9:F9) -> 395.76611 | H13: =SUM($B$9:G9) -> 483.92598 | I13: =SUM($B$9:H9) -> 590.01115 | J13: =SUM($B$9:I9) -> 696.09632 | ... BJ13: =SUM($B$9:BI9) -> 2565
A14: Compensation to buyers | B14: =IF(AND(Fin_Inputs!$C$17>0,B$4>Fin_Activities!$C$50,B$4<=Fin_Activities!$C$49),Fin_Inputs!$C$17/12*B13,0) -> 0 | C14: =IF(AND(Fin_Inputs!$C$17>0,C$4>Fin_Activities!$C$50,C$4<=Fin_Activities!$C$49),Fin_Inputs!$C$17/12*C13,0) -> 0 | D14: =IF(AND(Fin_Inputs!$C$17>0,D$4>Fin_Activities!$C$50,D$4<=Fin_Activities!$C$49),Fin_Inputs!$C$17/12*D13,0) -> 0 | E14: =IF(AND(Fin_Inputs!$C$17>0,E$4>Fin_Activities!$C$50,E$4<=Fin_Activities!$C$49),Fin_Inputs!$C$17/12*E13,0) -> 0 | F14: =IF(AND(Fin_Inputs!$C$17>0,F$4>Fin_Activities!$C$50,F$4<=Fin_Activities!$C$49),Fin_Inputs!$C$17/12*F13,0) -> 0 | G14: =IF(AND(Fin_Inputs!$C$17>0,G$4>Fin_Activities!$C$50,G$4<=Fin_Activities!$C$49),Fin_Inputs!$C$17/12*G13,0) -> 0 | H14: =IF(AND(Fin_Inputs!$C$17>0,H$4>Fin_Activities!$C$50,H$4<=Fin_Activities!$C$49),Fin_Inputs!$C$17/12*H13,0) -> 0 | I14: =IF(AND(Fin_Inputs!$C$17>0,I$4>Fin_Activities!$C$50,I$4<=Fin_Activities!$C$49),Fin_Inputs!$C$17/12*I13,0) -> 0 | ... BJ14: =IF(AND(Fin_Inputs!$C$17>0,BJ$4>Fin_Activities!$C$50,BJ$4<=Fin_Activities!$C$49),Fin_Inputs!$C$17/12*BJ13,0) -> 0
A15: Project cash flow | B15: =B11-B12-B6-B7-B5-B14 -> -2650 | C15: =C11-C12-C6-C7-C5-C14 -> -26.405558 | D15: =D11-D12-D6-D7-D5-D14 -> -60.018526 | E15: =E11-E12-E6-E7-E5-E14 -> -49.936511 | F15: =F11-F12-F6-F7-F5-F14 -> -63.488614 | G15: =G11-G12-G6-G7-G5-G14 -> -45.82555 | H15: =H11-H12-H6-H7-H5-H14 -> -52.703203 | I15: =I11-I12-I6-I7-I5-I14 -> -52.703203 | ... BJ15: =BJ11-BJ12-BJ6-BJ7-BJ5-BJ14 -> 0
A16: Debt opening | B16: =0 -> 0 | C16: =B22 -> 0 | D16: =C22 -> 15.843335 | E16: =D22 -> 51.986824 | F16: =E22 -> 82.383088 | G16: =F22 -> 121.16458 | H16: =G22 -> 149.67226 | I16: =H22 -> 182.54472 | J16: =I22 -> 215.69183 | ... BJ16: =BI22 -> 0
A17: Interest | B17: =B16*Fin_Inputs!$C$26 -> 0 | C17: =C16*Fin_Inputs!$C$26 -> 0 | D17: =D16*Fin_Inputs!$C$26 -> 0.13237353 | E17: =E16*Fin_Inputs!$C$26 -> 0.434358 | F17: =F16*Fin_Inputs!$C$26 -> 0.68832353 | G17: =G16*Fin_Inputs!$C$26 -> 1.0123489 | H17: =H16*Fin_Inputs!$C$26 -> 1.250535 | I17: =I16*Fin_Inputs!$C$26 -> 1.5251895 | ... BJ17: =BJ16*Fin_Inputs!$C$26 -> 0
A18: Funding need | B18: =MAX(0,-B15) -> 2650 | C18: =MAX(0,-C15) -> 26.405558 | D18: =MAX(0,-D15) -> 60.018526 | E18: =MAX(0,-E15) -> 49.936511 | F18: =MAX(0,-F15) -> 63.488614 | G18: =MAX(0,-G15) -> 45.82555 | H18: =MAX(0,-H15) -> 52.703203 | I18: =MAX(0,-I15) -> 52.703203 | ... BJ18: =MAX(0,-BJ15) -> 0
A19: Debt draw | B19: =0 -> 0 | C19: =C18*Fin_Inputs!$C$12 -> 15.843335 | D19: =D18*Fin_Inputs!$C$12 -> 36.011115 | E19: =E18*Fin_Inputs!$C$12 -> 29.961907 | F19: =F18*Fin_Inputs!$C$12 -> 38.093169 | G19: =G18*Fin_Inputs!$C$12 -> 27.49533 | H19: =H18*Fin_Inputs!$C$12 -> 31.621922 | I19: =I18*Fin_Inputs!$C$12 -> 31.621922 | J19: =J18*Fin_Inputs!$C$12 -> 35.220553 | ... BJ19: =BJ18*Fin_Inputs!$C$12 -> 0
A20: Surplus | B20: =MAX(0,B15) -> 0 | C20: =MAX(0,C15) -> 0 | D20: =MAX(0,D15) -> 0 | E20: =MAX(0,E15) -> 0 | F20: =MAX(0,F15) -> 0 | G20: =MAX(0,G15) -> 0 | H20: =MAX(0,H15) -> 0 | I20: =MAX(0,I15) -> 0 | ... BJ20: =MAX(0,BJ15) -> 0
A21: Repay | B21: =MIN(B16+B17+B19,B20) -> 0 | C21: =MIN(C16+C17+C19,C20) -> 0 | D21: =MIN(D16+D17+D19,D20) -> 0 | E21: =MIN(E16+E17+E19,E20) -> 0 | F21: =MIN(F16+F17+F19,F20) -> 0 | G21: =MIN(G16+G17+G19,G20) -> 0 | H21: =MIN(H16+H17+H19,H20) -> 0 | I21: =MIN(I16+I17+I19,I20) -> 0 | ... BJ21: =MIN(BJ16+BJ17+BJ19,BJ20) -> 0
A22: Debt closing | B22: =B16+B17+B19-B21 -> 0 | C22: =C16+C17+C19-C21 -> 15.843335 | D22: =D16+D17+D19-D21 -> 51.986824 | E22: =E16+E17+E19-E21 -> 82.383088 | F22: =F16+F17+F19-F21 -> 121.16458 | G22: =G16+G17+G19-G21 -> 149.67226 | H22: =H16+H17+H19-H21 -> 182.54472 | I22: =I16+I17+I19-I21 -> 215.69183 | ... BJ22: =BJ16+BJ17+BJ19-BJ21 -> 0
A23: Equity cash flow | B23: =-(B18-B19)+(B20-B21) -> -2650 | C23: =-(C18-C19)+(C20-C21) -> -10.562223 | D23: =-(D18-D19)+(D20-D21) -> -24.00741 | E23: =-(E18-E19)+(E20-E21) -> -19.974604 | F23: =-(F18-F19)+(F20-F21) -> -25.395446 | G23: =-(G18-G19)+(G20-G21) -> -18.33022 | H23: =-(H18-H19)+(H20-H21) -> -21.081281 | I23: =-(I18-I19)+(I20-I21) -> -21.081281 | ... BI23: =-(BI18-BI19)+(BI20-BI21) -> 0 | BJ23: =-(BJ18-BJ19)+(BJ20-BJ21)-BJ22 -> 0
A27: Results | B27: Current scenario: | C27: =IF(AND(Fin_Inputs!$C$21=1,Fin_Inputs!$C$23=0),"Plan",IF(AND(Fin_Inputs!$C$21=1.1,Fin_Inputs!$C$23=0),"Flat10",IF(AND(Fin_Inputs!$C$21=1,Fin_Inputs!$C$23=60,Fin_Inputs!$C$22=$J$27),"Delay60","No tool value for these settings"))) -> Plan | I27: Tool delay activity: | J27: A28
A28: Measure | B28: Excel | C28: Tool: Plan | D28: Tool: Flat10 | E28: Tool: Delay60 | F28: Tool (current scenario) | G28: Difference | H28: Tolerance | I28: Result
A29: Project duration (days) | B29: =Fin_Activities!$C$47 -> 700 | C29: 700 | D29: 700 | E29: 760 | F29: =IF($C$27="Plan",C29,IF($C$27="Flat10",D29,IF($C$27="Delay60",E29,""))) -> 700 | G29: =IF(F29="","",ABS(B29-F29)) -> 0 | H29: 0.0001 | I29: =IF(F29="","Pending",IF(G29<=H29,"Pass","Fail")) -> Pass
A30: Construction cost incl. overheads (Rs lakh) | B30: =SUM($B$6:$BJ$7) -> 3777.85 | C30: 3777.85 | D30: 4155.635 | E30: 3804.85 | F30: =IF($C$27="Plan",C30,IF($C$27="Flat10",D30,IF($C$27="Delay60",E30,""))) -> 3777.85 | G30: =IF(F30="","",ABS(B30-F30)) -> 0 | H30: 0.01 | I30: =IF(F30="","Pending",IF(G30<=H30,"Pass","Fail")) -> Pass
A31: Project NPV (Rs lakh) | B31: =B15+NPV(Fin_Inputs!$C$27,C15:BJ15) -> 613.96567 | C31: 613.96567 | D31: 274.17758 | E31: 510.09425 | F31: =IF($C$27="Plan",C31,IF($C$27="Flat10",D31,IF($C$27="Delay60",E31,""))) -> 613.96567 | G31: =IF(F31="","",ABS(B31-F31)) -> 0 | H31: 0.01 | I31: =IF(F31="","Pending",IF(G31<=H31,"Pass","Fail")) -> Pass
A32: Equity NPV (Rs lakh) | B32: =B23+NPV(Fin_Inputs!$C$28,C23:BJ23) -> 313.48261 | C32: 313.48261 | D32: -3.5416977 | E32: 200.26475 | F32: =IF($C$27="Plan",C32,IF($C$27="Flat10",D32,IF($C$27="Delay60",E32,""))) -> 313.48261 | G32: =IF(F32="","",ABS(B32-F32)) -> 0 | H32: 0.01 | I32: =IF(F32="","Pending",IF(G32<=H32,"Pass","Fail")) -> Pass
A33: Project IRR (annual) | B33: =(1+IRR($B$15:$BJ$15,0.01))^12-1 -> 0.19707914 | C33: 0.19707914 | D33: 0.15320115 | E33: 0.17986901 | F33: =IF($C$27="Plan",C33,IF($C$27="Flat10",D33,IF($C$27="Delay60",E33,""))) -> 0.19707914 | G33: =IF(F33="","",ABS(B33-F33)) -> 3.0808689e-15 | H33: 0.0001 | I33: =IF(F33="","Pending",IF(G33<=H33,"Pass","Fail")) -> Pass
A34: Equity IRR (annual) | B34: =(1+IRR($B$23:$BJ$23,0.01))^12-1 -> 0.20619712 | C34: 0.20619712 | D34: 0.15948219 | E34: 0.18786674 | F34: =IF($C$27="Plan",C34,IF($C$27="Flat10",D34,IF($C$27="Delay60",E34,""))) -> 0.20619712 | G34: =IF(F34="","",ABS(B34-F34)) -> 0 | H34: 0.0001 | I34: =IF(F34="","Pending",IF(G34<=H34,"Pass","Fail")) -> Pass
A35: Interest during construction (Rs lakh) | B35: =SUMPRODUCT(($B$4:$BJ$4<=Fin_Activities!$C$49)*$B$17:$BJ$17) -> 84.120813 | C35: 84.120813 | D35: 109.50646 | E35: 98.546997 | F35: =IF($C$27="Plan",C35,IF($C$27="Flat10",D35,IF($C$27="Delay60",E35,""))) -> 84.120813 | G35: =IF(F35="","",ABS(B35-F35)) -> 0 | H35: 0.01 | I35: =IF(F35="","Pending",IF(G35<=H35,"Pass","Fail")) -> Pass
A36: Total interest (Rs lakh) | B36: =SUM($B$17:$BJ$17) -> 94.176133 | C36: 94.176133 | D36: 124.88921 | E36: 109.11623 | F36: =IF($C$27="Plan",C36,IF($C$27="Flat10",D36,IF($C$27="Delay60",E36,""))) -> 94.176133 | G36: =IF(F36="","",ABS(B36-F36)) -> 0 | H36: 0.01 | I36: =IF(F36="","Pending",IF(G36<=H36,"Pass","Fail")) -> Pass
A37: Peak debt (Rs lakh) | B37: =MAX($B$22:$BJ$22) -> 842.61081 | C37: 842.61081 | D37: 1094.6675 | E37: 873.237 | F37: =IF($C$27="Plan",C37,IF($C$27="Flat10",D37,IF($C$27="Delay60",E37,""))) -> 842.61081 | G37: =IF(F37="","",ABS(B37-F37)) -> 0 | H37: 0.01 | I37: =IF(F37="","Pending",IF(G37<=H37,"Pass","Fail")) -> Pass
A38: Compensation to buyers (Rs lakh) | B38: =SUM($B$14:$BJ$14) -> 0 | C38: 0 | D38: 0 | E38: 0 | F38: =IF($C$27="Plan",C38,IF($C$27="Flat10",D38,IF($C$27="Delay60",E38,""))) -> 0 | G38: =IF(F38="","",ABS(B38-F38)) -> 0 | H38: 0.01 | I38: =IF(F38="","Pending",IF(G38<=H38,"Pass","Fail")) -> Pass
A39: Undiscounted profit (Rs lakh) | B39: =SUM($B$15:$BJ$15) -> 1951.15 | C39: 1951.15 | D39: 1573.365 | E39: 1924.15 | F39: =IF($C$27="Plan",C39,IF($C$27="Flat10",D39,IF($C$27="Delay60",E39,""))) -> 1951.15 | G39: =IF(F39="","",ABS(B39-F39)) -> 0 | H39: 0.01 | I39: =IF(F39="","Pending",IF(G39<=H39,"Pass","Fail")) -> Pass
A41: Horizon check | B41: =IF(Fin_Activities!$C$49+Fin_Inputs!$C$10+1>60,"Extend month columns","OK") -> OK
A44: Hand checks by calculator (fill yellow, do not copy from Excel)
A45: Item | B45: Excel | C45: Your hand value | D45: Difference
A46: Equity cash flow in month 0 = -(land + approvals) | B46: =B23 -> -2650 | D46: =IF(C46="","",ABS(B46-C46))
A47: Overheads in month 1 = overheads per month | B47: =C7 -> 12 | D47: =IF(C47="","",ABS(B47-C47))
A48: Construction spend in month 1 (sum of cost x days in month 1 / duration) | B48: =C6 -> 51.2 | D48: =IF(C48="","",ABS(B48-C48))
A49: Presale collections in month 1 = presale share x revenue x month-1 share | B49: =C9 -> 37.545349 | D49: =IF(C49="","",ABS(B49-C49))
A50: Interest in month 3 = month-3 opening debt x monthly rate | B50: =E17 -> 0.434358 | D50: =IF(C50="","",ABS(B50-C50))
A51: Completion month = CEILING(project duration / 30) | B51: =Fin_Activities!$C$49 -> 24 | D51: =IF(C51="","",ABS(B51-C51))
